Workbook

Sheet 1. Resumo Executivo
A1: IMPULSO — PLANO DE NEGÓCIOS COMPLETO
B2: Agência boutique de implementação de e-commerce e sites institucionais — análise da banca de especialistas
A4: IDENTIDADE DA EMPRESA
B5: Nome da empresa | C5: Impulso
B6: Posicionamento | C6: Implementação rápida e profissional de lojas virtuais e sites institucionais para PMEs e empreendedores digitais
B7: Público-alvo (ICP) | C7: PMEs físicas migrando para digital (Carla); empreendedores DTC em validação (Rodrigo); B2B PME catálogo digital (Mariana)
B8: Proposta de valor | C8: "Sua loja online profissional no ar em 48 horas — pronta para vender — com método, suporte e crescimento contínuo, sem freelancer sumido nem agência que demora 3 meses."
B9: Diferenciais | C9: Método Impulso 48h proprietário (checklist + biblioteca de blocos + integrações pré-configuradas + kit IA); especialização vertical; conversão projeto→recorrência
B10: Serviços | C10: 1) Projeto 48 Horas (Start/Pro/Premium) | 2) Projetos personalizados | 3) Planos mensais de suporte (Essencial/Pro/Growth) | 4) Receita de parceria com plataformas (20% MRR) | 5) Gestão de tráfego pago
B11: Modelo de receita | C11: Mix transacional (projetos) + recorrente (suporte + parceria + gestão). Meta 24 meses: 50% receita recorrente
B12: Regime tributário | C12: Simples Nacional, Anexo III com Fator R ≥ 28% (pró-labore é a alavanca). Premissa de 12% é conservadora — efetivo real é 6-8,4% até R$ 30k/mês
B13: Operação | C13: Home office, 2 sócios sêniors, capacidade combinada ~180h/mês de execução pura
A15: PRINCIPAIS PREMISSAS
B16: Premissa | C16: Valor | D16: Origem
B17: Número de sócios operacionais | C17: ='2. Premissas'!C5 | E17: Definido pelo usuário
B18: Pró-labore por sócio (mensal) | C18: ='2. Premissas'!C7 | E18: Definido pelo usuário
B19: Pró-labore total mensal | C19: ='2. Premissas'!C9 | E19: =2 sócios × R$ 4.000
B20: Pró-labore anual total | C20: ='2. Premissas'!C10 | E20: =mensal × 12
B21: Horas produtivas mensais (2 sócios) | C21: ='2. Premissas'!C19 | E21: Análise operacional
B22: Custo/hora interno (R$) | C22: ='2. Premissas'!C68 | E22: =(CF total) / horas produtivas
B23: Margem recomendada | C23: ='2. Premissas'!C27 | E23: Editável
B24: Imposto Simples efetivo (premissa) | C24: ='2. Premissas'!C31 | E24: Editável — confer. Anexo III
B25: Reserva de capital de giro recomendada | C25: ='2. Premissas'!C65 | E25: 6× burn (recomendação CFO)
A27: INDICADORES-CHAVE DOS 3 CENÁRIOS (linkados à aba 12)
B28: Indicador | C28: Pessimista | D28: Realista | E28: Otimista | F28: Como é calculado
B29: Receita bruta anual | C29: ='12. Cenários'!P11 | D29: ='12. Cenários'!P38 | E29: ='12. Cenários'!P65 | F29: Soma 12 meses de cada cenário
B30: Receita média mensal | C30: ='12. Cenários'!P11/12 | D30: ='12. Cenários'!P38/12 | E30: ='12. Cenários'!P65/12 | F30: Anual ÷ 12
B31: Lucro líquido anual | C31: ='12. Cenários'!P17 | D31: ='12. Cenários'!P44 | E31: ='12. Cenários'!P71 | F31: Soma do lucro líquido 12m
B32: Margem líquida média | C32: ='12. Cenários'!P18 | D32: ='12. Cenários'!P45 | E32: ='12. Cenários'!P72 | F32: Lucro anual ÷ Receita anual
B33: Caixa acumulado mês 12 | C33: ='12. Cenários'!O19 | D33: ='12. Cenários'!O46 | E33: ='12. Cenários'!O73 | F33: Caixa final do mês 12
B34: Ponto de equilíbrio mensal | C34: ='15. Ponto Equilíbrio'!C12 | D34: ='15. Ponto Equilíbrio'!C12 | E34: ='15. Ponto Equilíbrio'!C12 | F34: CF ÷ (1 − deduções variáveis)
B35: Pró-labore total mensal | C35: ='2. Premissas'!C9 | D35: ='2. Premissas'!C9 | E35: ='2. Premissas'!C9 | F35: Premissa editável
B36: Custos fixos mensais (sem pró-labore) | C36: ='2. Premissas'!C62 | D36: ='2. Premissas'!C62 | E36: ='2. Premissas'!C62 | F36: Soma fixos da aba 2
B37: Payback estimado | C37: Inviável s/ aporte | D37: ~9 meses (caixa+ no mês 6) | E37: ~4 meses | F37: Análise CFO
A39: CONCLUSÃO EXECUTIVA DO SQUAD
B40: 🟢 VIÁVEL no Realista (margem líquida ~24%, payback ~9m) e robusto no Otimista (margem 44%). 🔴 Pessimista é inviável sem aporte ou ajuste de pró-labore. Os 3 AJUSTES NÃO-NEGOCIÁVEIS identificados pelo squad: 1) Pró-labore ESCALONADO — começar com R$ 3k/sócio (mês 1-3) → R$ 3,5k (4-6) → R$ 4k (7+) quando MRR > R$ 10k. Sustenta o Fator R do Anexo III (28%) e protege o caixa. 2) Escopo do 48h TAXATIVO — máximo 20 SKUs, 1 gateway, 1 frete, 4 páginas, plataformas Shopify/Nuvemshop/Tray. Woo fora do 48h. Sem isso, vira processo no PROCON (art. 30, 37 CDC). 3) Foco comercial em MRR — meta de 50% de receita recorrente até 24 meses. Cada R$ 1 de MRR vale 3-5× R$ 1 de projeto. ⚠️ RISCO ESTRATÉGICO MAIOR (24-36 meses): comoditização do setup básico por IA generativa (Shopify Magic, Wix ADI). A tese precisa migrar de 'implementador' para 'operador de crescimento de PMEs digitais' — vender resultado de vendas, não apenas loja no ar. ✅ AÇÕES OBRIGATÓRIAS antes da 1ª venda: constituir LTDA + CNAEs corretos + Simples; contrato dual-track (B2B/B2C); Política do Projeto 48 Horas com aceite eletrônico; LGPD (DPA); registrar marca no INPI; reserva de R$ 50k de capital de giro.

Sheet 2. Premissas
A1: PREMISSAS GERAIS — EDITE AQUI E TODA A PLANILHA SE ATUALIZA
B2: Células em AMARELO são premissas editáveis. Verde = fórmulas (não editar). Cinza = referência. | E2: REFERÊNCIAS-CHAVE: C9=Pró-labore total | C19=Horas produtivas | C62=Custos fixos s/PL | C63=CF total | C68=Custo/h | C70=Deduções var | C31=Imposto
A4: SÓCIOS E PRÓ-LABORE
B5: Número de sócios operacionais | C5: 2 | D5: un | E5: Definição da operação
B7: Pró-labore mensal por sócio (R$) | C7: 4000 | D7: R$/mês | E7: Premissa do usuário — R$ 4.000/sócio
B8: INSS sócio (11% sobre pró-labore individual) | C8: =C7*0.11 | D8: R$/mês | E8: Art. 21 Lei 8.212/91 (até teto)
B9: Pró-labore TOTAL mensal | C9: =C7*C5 | D9: R$/mês | E9: Fórmula = pró-labore × sócios
B10: Pró-labore TOTAL anual | C10: =C9*12 | D10: R$/ano | E10: Fórmula = mensal × 12
B11: INSS sócios TOTAL mensal | C11: =C8*C5 | D11: R$/mês | E11: Soma do INSS dos sócios
A13: CAPACIDADE OPERACIONAL
B14: Dias úteis por mês | C14: 22 | D14: dias | E14: Premissa padrão BR
B15: Horas/dia por sócio | C15: 8 | D15: h | E15: Jornada
B16: Horas BRUTAS mensais por sócio | C16: =C14*C15 | D16: h | E16: Fórmula = dias × horas/dia
B17: Horas brutas mensais TOTAIS (2 sócios) | C17: =C16*C5 | D17: h | E17: Fórmula = horas/sócio × sócios
B18: % de horas produtivas reais (descontado comercial, admin, atendimento) | C18: 0.5 | D18: % | E18: Análise operacional: ~50% (vendas 15% + atendimento 10% + pós-venda 10% + admin 8% + gestão 7%)
B19: Horas PRODUTIVAS mensais (execução pura) | C19: =C17*C18 | D19: h | E19: Fórmula. Padrão de planejamento: 176h
B20: Ganho médio de produtividade com IA (%) | C20: 0.25 | D20: % | E20: Análise operacional — ganho real médio (não 80%+ ilusório)
B21: Capacidade-alvo (% de utilização sustentável) | C21: 0.8 | D21: % | E21: Operar ≤80% para evitar burnout
B22: Horas FATURÁVEIS mensais (alvo) | C22: =C19*C21 | D22: h | E22: Horas produtivas × utilização alvo
A24: PRECIFICAÇÃO E MARGEM
B25: Valor/hora desejado (referência mercado) | C25: 250 | D25: R$/h | E25: Mercado: freela sênior R$ 150-400/h; agência R$ 200-600/h
B26: Margem MÍNIMA aceitável | C26: 0.2 | D26: % | E26: Piso para não vender no prejuízo
B27: Margem RECOMENDADA | C27: 0.4 | D27: % | E27: Saudável para serviços
B28: Margem PREMIUM (sem desconto) | C28: 0.55 | D28: % | E28: Preço de ancoragem
A30: IMPOSTOS E TAXAS DE PAGAMENTO
B31: Imposto Simples efetivo (premissa do projeto) | C31: 0.12 | D31: % | E31: Premissa do usuário. Real: 6% até R$ 180k; 8,4% até R$ 360k; 11% até R$ 720k (Anexo III)
B32: Taxa PIX (gateway) | C32: 0.005 | D32: % | E32: InfinitePay 0%; PagBank até 1,89%
B33: Taxa cartão à vista | C33: 0.035 | D33: % | E33: Stone 3,11%; PagBank D+30 3,19%; InfinitePay 2,69%
B34: Taxa cartão 3x | C34: 0.045 | D34: % | E34: Stone parcelado start 5,41%; média 4-5%
B35: Taxa cartão 6x | C35: 0.065 | D35: % | E35: Faixa intermediária
B36: Taxa cartão 10x | C36: 0.095 | D36: % | E36: Mercado Pago D+1 ~12,49%; InfinitePay 12x 8,99%
B37: Taxa cartão 12x | C37: 0.115 | D37: % | E37: Faixa iniciante MP até 22%; recomenda-se repassar juros >6x
B38: Inadimplência projetada (PCLD) | C38: 0.04 | D38: % | E38: B2B serviços BR — 4% conservador. Serasa: 55,2% inadimplência em serviços
A40: CUSTOS FIXOS MENSAIS (sem pró-labore)
B41: Internet empresarial (fibra 200-500 Mbps, 2 sócios) | C41: 200 | D41: R$/mês | E41: Vivo R$ 128,98; TIM R$ 119,99; média BR R$ 100-180
B42: Energia adicional home office (2 sócios) | C42: 80 | D42: R$/mês | E42: Enel SP R$ 0,91/kWh × ~45 kWh/sócio (R$ 40/sócio)
B43: Google Workspace Business Starter (2 usuários) | C43: 65 | D43: R$/mês | E43: R$ 32,72/user × 2 (anual)
B44: Ferramentas IA (ChatGPT Plus + Claude Pro) | C44: 220 | D44: R$/mês | E44: US$ 20 × 2 ≈ R$ 108 × 2
B45: Figma Professional (2 editores anual) | C45: 162 | D45: R$/mês | E45: US$ 15/editor × 2 ≈ R$ 81 × 2
B46: Canva Pro Teams | C46: 39 | D46: R$/mês | E46: R$ 470/ano = R$ 39/mês
B47: ClickUp Unlimited (2 users anual) | C47: 14 | D47: R$/mês | E47: R$ 7 × 2
B48: HubSpot CRM Free | C48: 0 | D48: R$/mês | E48: Gratuito
B49: Make Core / Zapier Starter | C49: 60 | D49: R$/mês | E49: Make US$ 10,59 ≈ R$ 57
B50: Hospedagem site Impulso + domínio | C50: 50 | D50: R$/mês | E50: Hostinger Premium + .com.br Registro.br R$ 40/ano
B51: Contabilidade especializada (recomendação contábil) | C51: 800 | D51: R$/mês | E51: Faixa: ME serviços R$ 400-1.200; especializada em TI R$ 700-1.200
B52: Certificado Digital A1 (R$ 220/ano) | C52: 20 | D52: R$/mês | E52: Necessário p/ NFS-e nacional
... B57: Outros custos administrativos / contingência | C57: 200 | D57: R$/mês | E57: Sindicato, taxas municipais, eventual
B58: SUBTOTAL CUSTOS FIXOS (sem pró-labore) | C58: =SUM(C41:C57) | D58: R$/mês | E58: Soma automática dos custos acima
B59: CUSTO FIXO TOTAL (com pró-labore + INSS) | C59: =C58+C9+C11 | D59: R$/mês | E59: Subtotal + pró-labore + INSS
A61: CÁLCULOS DERIVADOS (não editar)
B62: (CF40) Subtotal Custos Fixos (sem pró-labore) | C62: =C58 | D62: R$/mês | E62: Referência usada em outras abas
B63: Custo Fixo TOTAL (com pró-labore + INSS) | C63: =C62+C9+C11 | D63: R$/mês | E63: Base do ponto de equilíbrio
B64: Reserva capital de giro mínima (3× burn) | C64: =C63*3 | D64: R$ | E64: Recomendação CFO
B65: Reserva capital de giro RECOMENDADA (6× burn) | C65: =C63*6 | D65: R$ | E65: Recomendação CFO
B66: Reserva conservadora (12× burn) | C66: =C63*12 | D66: R$ | E66: Para cenário pessimista
B68: CUSTO/HORA INTERNO (piso) | C68: =C63/C19 | D68: R$/h | E68: =Custo fixo total / horas produtivas. Vender abaixo = prejuízo certo.
B69: Taxa cartão MÉDIA (ponderada das 6 modalidades) | C69: =AVERAGE(C32:C37) | D69: % | E69: Média simples; pode-se ponderar por mix real
B70: Deduções variáveis totais (imposto + taxa média + inad) | C70: =C31+C69+C38 | D70: % | E70: Usado no ponto de equilíbrio

Sheet 3. Pesquisa Mercado
A1: PESQUISA DE MERCADO E REFERÊNCIAS REAIS
B2: Dados consultados em 2026-06-10 — câmbio referência USD ≈ R$ 5,42 | EUR ≈ R$ 5,90
A4: A. PLATAFORMAS DE E-COMMERCE (preço mensal BRL e programas de parceria)
B5: Item | C5: Mínimo | D5: Médio | E5: Máximo | F5: Data | G5: Fonte / Observação
B6: Shopify Basic (US$ 39 anual US$ 29) | C6: 157 | D6: 211 | E6: 211 | F6: 2026-06-10 | G6: shopify.com/pricing — IOF 6,38%
B7: Shopify Grow (US$ 105 anual US$ 79) | C7: 428 | D7: 569 | E7: 569 | F7: 2026-06-10 | G7: shopify.com/pricing
B8: Shopify Advanced (US$ 399 anual US$ 299) | C8: 1621 | D8: 2163 | E8: 2163 | F8: 2026-06-10 | G8: shopify.com/pricing
B9: Shopify Partners — comissão recorrente | D9: 20% | F9: 2026-06-10 | G9: help.shopify.com/en/partners/partner-program/how-to-earn
B10: Tray — faixa de planos | C10: 19 | D10: 99 | E10: 449 | F10: 2026-06-10 | G10: tray.com.br/planos-precos
B11: Tray Partners — comissão recorrente | D11: 20-30% | F11: 2026-06-10 | G11: tray.com.br/partners
B12: Nuvemshop Essencial | C12: 59 | D12: 59 | E12: 59 | F12: 2026-06-10 | G12: nuvemshop.com.br/planos-e-precos
B13: Nuvemshop Impulso (plano homônimo) | C13: 139 | D13: 139 | E13: 139 | F13: 2026-06-10 | G13: nuvemshop.com.br/planos-e-precos
B14: Nuvemshop Escala | C14: 389 | D14: 389 | E14: 389 | F14: 2026-06-10 | G14: nuvemshop.com.br/planos-e-precos
B15: Nuvemshop Experts — comissão | D15: 20% | F15: 2026-06-10 | G15: atendimento.nuvemshop.com.br — comissões vigentes
B16: WooCommerce hospedagem entry (Hostinger/KingHost) | C16: 13 | D16: 30 | E16: 50 | F16: 2026-06-10 | G16: hostinger.com/br/tutoriais/wordpress-preco; site.king.host
B17: WooCommerce TCO total (hosp+plugins) | C17: 100 | D17: 250 | E17: 500 | F17: 2026-06-10 | G17: Composição — estimativa de mercado
B18: Wix Core eCommerce (US$ 29) | C18: 157 | D18: 157 | E18: 157 | F18: 2026-06-10 | G18: tooltester.com/wix
B19: BigCommerce Core (US$ 39, cap US$ 50k/ano) | C19: 211 | D19: 211 | E19: 211 | F19: 2026-06-10 | G19: bigcommerce.com/essentials/pricing
B20: VTEX Business (anual R$ 60k) | C20: 5000 | D20: 5000 | E20: 5000 | F20: 2026-06-10 | G20: assine.vtex.com/vtex-commerce-suite-new-business
A22: B. PREÇOS DE SERVIÇOS — REFERÊNCIAS DE MERCADO BR
B23: Item | C23: Mínimo | D23: Médio | E23: Máximo | F23: Data | G23: Fonte / Observação
B24: Implementação e-commerce ENTRY (Nuvemshop/Tray template) | C24: 3000 | D24: 6000 | E24: 10000 | F24: 2026-06-10 | G24: mathcreator.com.br; safiradesign.com.br
B25: Implementação Shopify INTERMEDIÁRIO | C25: 8000 | D25: 18000 | E25: 25000 | F25: 2026-06-10 | G25: litextension.com/pt/blog/shopify-pricing; simplesinovacao.com
B26: Implementação Shopify/VTEX PREMIUM (custom) | C26: 25000 | D26: 35000 | E26: 60000 | F26: 2026-06-10 | G26: litextension.com
B27: Site institucional simples | C27: 3000 | D27: 5000 | E27: 6000 | F27: 2026-06-10 | G27: hostwp.com.br; safiradesign.com.br
B28: Site institucional premium | C28: 7000 | D28: 11000 | E28: 15000 | F28: 2026-06-10 | G28: hostwp.com.br; mathcreator.com.br
B29: Landing page básica (template) | C29: 300 | D29: 600 | E29: 900 | F29: 2026-06-10 | G29: gabrieldosite.com.br
B30: Landing page profissional | C30: 1200 | D30: 2500 | E30: 4000 | F30: 2026-06-10 | G30: bluepaper.io
B31: Landing page estratégica c/ funil/automação | C31: 2000 | D31: 4500 | E31: 8000 | F31: 2026-06-10 | G31: bluepaper.io
B32: Migração de plataforma (ex: VTEX→Shopify) | C32: 8000 | D32: 18000 | E32: 40000 | F32: 2026-06-10 | G32: hulkapps.com
B33: Integração ERP (Bling/Tiny/Omie) projeto único | C33: 490 | D33: 1500 | E33: 4000 | F33: 2026-06-10 | G33: brauerecommerce.com.br
B34: SEO técnico — auditoria pontual | C34: 1200 | D34: 4000 | E34: 8000 | F34: 2026-06-10 | G34: juanmoura.com; profissionalseo.com.br
B35: SEO técnico — mensal contínuo | C35: 2000 | D35: 5000 | E35: 15000 | F35: 2026-06-10 | G35: juanmoura.com
... B39: Squad agência (4-5 pessoas/mês) | C39: 60000 | D39: 90000 | E39: 120000 | F39: 2026-06-10 | G39: numerando.com.br
A41: C. PLANOS MENSAIS DE SUPORTE/MANUTENÇÃO BR
B42: Item | C42: Mínimo | D42: Médio | E42: Máximo | F42: Data | G42: Fonte / Observação
B43: WP Essencial 1 site, 2h, manutenção preventiva | C43: 199 | D43: 250 | E43: 300 | F43: 2026-06-10 | G43: profissionalwp.dev.br
B44: Loja virtual mid (6h, não cumulativas) | C44: 600 | D44: 900 | E44: 1200 | F44: 2026-06-10 | G44: linkwell.com.br — faixa estimada
B45: Mid-tier (10-20h, SLA 24h) | C45: 1500 | D45: 2500 | E45: 3500 | F45: 2026-06-10 | G45: ae.digital — estimativa
B46: Premium (30h+, SLA 4h úteis) | C46: 4000 | D46: 6000 | E46: 8000 | F46: 2026-06-10 | G46: found.pt — estimativa
A48: D. TAXAS DE CARTÃO BR 2025-2026 (online com antecipação automática)
B49: Item | C49: Mínimo | D49: Médio | E49: Máximo | F49: Data | G49: Fonte / Observação
B50: Stone — Débito | À vista | Parcelado start | C50: 1,25% | D50: 3,11% | E50: 5,41% | F50: 2026-06-10 | G50: calculadoradetaxas.com.br/stone
B51: Mercado Pago — 12x D+14 | D+1 | D+0 | C51: 9,98% | D51: 12,49% | E51: 14,99% | F51: 2026-06-10 | G51: blog.jota.ai/taxas-maquininha-mercadopago-2026
B52: PagBank — Débito | Crédito D+30 | D+0 | C52: 1,99% | D52: 3,19% | E52: 4,99% | F52: 2026-06-10 | G52: pagbank.com.br/maquininhas/taxas-e-tarifas
B53: InfinitePay — Débito | Crédito vista | 12x | C53: 0,75% | D53: 2,69% | E53: 8,99% | F53: 2026-06-10 | G53: infinitepay.io/taxas
B54: InfinitePay — PIX | C54: 0% | D54: 0% | E54: 0% | F54: 2026-06-10 | G54: infinitepay.io/pix
B55: Cielo — Débito | Crédito vista (entry) | C55: 1,07% | D55: 3,48% | E55: — | F55: 2026-06-10 | G55: calculadoradetaxas.com.br/cielo
B56: Cielo — Antecipação manual a.m. | C56: 1,49% | D56: 2,5% | E56: 3,5% | F56: 2026-06-10 | G56: antecipafacil.com.br
B57: Inadimplência B2B BR (Serasa dez/25) | C57: 8,9 mi empresas | D57: R$ 213 bi dívida | E57: 55,2% serviços | F57: 2026-06-10 | G57: serasa.com.br/limpa-nome/mapa-inadimplencia
A59: E. FERRAMENTAS — preço mensal (BRL ou USD convertido)
B60: Item | C60: Mínimo | D60: Médio | E60: Máximo | F60: Data | G60: Fonte / Observação
B61: ChatGPT Plus (US$ 20) | C61: 108 | D61: 108 | E61: 108 | F61: 2026-06-10 | G61: openai.com/pricing
B62: ChatGPT Team anual (US$ 25/seat) | C62: 135 | D62: 135 | E62: 135 | F62: 2026-06-10 | G62: openai.com/pricing
B63: Claude Pro (US$ 20) | C63: 108 | D63: 108 | E63: 108 | F63: 2026-06-10 | G63: claude.com/pricing
B64: Claude Team Standard anual (US$ 20/seat, min 5) | C64: 108 | D64: 108 | E64: 108 | F64: 2026-06-10 | G64: claude.com/pricing
B65: Cursor Pro (US$ 20) | C65: 108 | D65: 108 | E65: 108 | F65: 2026-06-10 | G65: cursor.com/pricing
B66: GitHub Copilot Pro (US$ 10) | C66: 54 | D66: 54 | E66: 54 | F66: 2026-06-10 | G66: github.com/features/copilot/plans
B67: Figma Professional anual (US$ 15/editor) | C67: 81 | D67: 81 | E67: 81 | F67: 2026-06-10 | G67: figma.com/pricing
B68: Canva Pro anual (1 pessoa) | C68: 24 | D68: 24 | E68: 24 | F68: 2026-06-10 | G68: canva.com/pt_br/precos
B69: Canva Teams (até 5 pessoas) | C69: 39 | D69: 39 | E69: 39 | F69: 2026-06-10 | G69: darlanevandro.com.br
B70: Adobe Creative Cloud Standard (BR atual) | C70: 249 | D70: 249 | E70: 320 | F70: 2026-06-10 | G70: tecnoblog.net (vigente desde ago/25)
B71: Make Core Starter (US$ 10,59) | C71: 57 | D71: 57 | E71: 57 | F71: 2026-06-10 | G71: toolradar.com/blog/zapier-pricing-2026
B72: Zapier Starter (US$ 19,99) | C72: 108 | D72: 108 | E72: 108 | F72: 2026-06-10 | G72: toolradar.com
... B87: Domínio .com.br Registro.br (R$ 40/ano) | C87: 3 | D87: 3 | E87: 3 | F87: 2026-06-10 | G87: registro.br — oficial
A89: F. TRÁFEGO PAGO — fee mensal por faixa de verba do cliente (BR)
B90: Item | C90: Mínimo | D90: Médio | E90: Máximo | F90: Data | G90: Fonte / Observação
B91: Cliente até R$ 2k/mês mídia | C91: 750 | D91: 1200 | E91: 1700 | F91: 2026-06-10 | G91: wisedatamarketing.com; atriomarketing.site
B92: Cliente R$ 2-5k mídia | C92: 1500 | D92: 2250 | E92: 3000 | F92: 2026-06-10 | G92: spotmkt.com.br; rocketmidia.com
B93: Cliente R$ 5-10k mídia | C93: 2500 | D93: 3750 | E93: 5000 | F93: 2026-06-10 | G93: spotmkt.com.br
B94: Cliente >R$ 10k mídia | C94: 5000 | D94: 10000 | E94: 20000 | F94: 2026-06-10 | G94: wisedatamarketing.com
B95: Modelo % sobre verba (alternativa) | C95: 10% | D95: 15% | E95: 20% | F95: 2026-06-10 | G95: atriomarketing.site
B96: Setup inicial campanhas (avulso) | C96: 500 | D96: 1500 | E96: 3000 | F96: 2026-06-10 | G96: spotmkt.com.br — faixa estimada
B97: ⚠️ Aumento Meta Ads BR jan/2026 (PIS/Cofins/ISS) | C97: +12,15% | D97: — | E97: — | F97: 2026-06-10 | G97: atriomarketing.site/blog
A99: G. TRIBUTAÇÃO E CONTABILIDADE — referências reais
B100: Item | C100: Mínimo | D100: Médio | E100: Máximo | F100: Data | G100: Fonte / Observação
B101: Faixa RBT12 | C101: Alíq. nominal | D101: Parcela a deduzir | E101: Alíq. efetiva (topo) | F101: Anexo | G101: Fonte
B102: Até R$ 180.000 | C102: 6,00% | D102: R$ 0 | E102: 6,00% | F102: III (Fator R ≥ 28%) | G102: Conube / Contabilizei — Anexo III
B103: R$ 180k-360k | C103: 11,20% | D103: R$ 9.360 | E103: 8,40% | F103: III | G103: conube.com.br/blog/anexo-3-tabela-simples-nacional
B104: R$ 360k-720k | C104: 13,50% | D104: R$ 17.640 | E104: 11,05% | F104: III | G104: contabilizei.com.br/contabilidade-online/anexo-3-simples-nacional
B105: R$ 720k-1,8M | C105: 16,00% | D105: R$ 35.640 | E105: 14,02% | F105: III | G105: contabilizei.com.br
B106: R$ 1,8M-3,6M | C106: 21,00% | D106: R$ 125.640 | E106: — | F106: III | G106: contabilizei.com.br
B107: R$ 3,6M-4,8M (teto Simples) | C107: 33,00% | D107: R$ 648.000 | E107: — | F107: III | G107: contabilizei.com.br
A109: G.1 — Honorários contábeis 2026 (livremente pactuados — CRC)
B110: Item | C110: Mínimo | D110: Médio | E110: Máximo | F110: Data | G110: Fonte
B111: ME Simples Nacional faixa típica | C111: 259 | D111: 489 | E111: 900 | F111: 2026-06-10 | G111: ohub.com.br/precos/contabilidade-mensal
B112: Contabilizei (online) | C112: 195 | D112: 195 | E112: 195 | F112: 2026-06-10 | G112: contabilizei.com.br/quanto-custa
B113: Contajá (online) | C113: 137 | D113: 137 | E113: 137 | F113: 2026-06-10 | G113: contaja.com.br
B114: Agilize (online) | C114: 259 | D114: 259 | E114: 259 | F114: 2026-06-10 | G114: artigos.agilize.com.br
B115: Contador ESPECIALIZADO em TI/agência (recomendado) | C115: 700 | D115: 900 | E115: 1200 | F115: 2026-06-10 | G115: Mercado especializado
A117: H. CUSTOS HOME OFFICE
B118: Item | C118: Mínimo | D118: Médio | E118: Máximo | F118: Data | G118: Fonte / Observação
B119: Vivo Empresas Fibra 600 Mbps | C119: 128.98 | D119: 128.98 | E119: 128.98 | F119: 2026-06-10 | G119: minhaconexao.com.br
B120: TIM Ultrafibra 500 Mbps | C120: 119.99 | D120: 139.99 | E120: 159.99 | F120: 2026-06-10 | G120: minhaconexao.com.br
B121: Claro Empresas 600 Mbps (promo 6m) | C121: 64.9 | D121: 64.9 | E121: 64.9 | F121: 2026-06-10 | G121: planos.claro.com.br/empresas — atenção pós-promoção
B122: Faixa 200-500 Mbps empresarial (mercado) | C122: 100 | D122: 140 | E122: 180 | F122: 2026-06-10 | G122: melhorplano.net
B123: kWh Enel SP (B1, bandeira verde, c/ impostos) | C123: 0.91 | D123: 0.91 | E123: 0.91 | F123: 2026-06-10 | G123: custosolar.com; calculadoraenergia.com.br
B124: kWh média nacional | C124: 0.68 | D124: 0.68 | E124: 0.68 | F124: 2026-06-10 | G124: custosolar.com
B125: kWh Light RJ (mais cara) | C125: 1.47 | D125: 1.47 | E125: 1.47 | F125: 2026-06-10 | G125: clarke.com.br/mapa-tarifas
B126: kWh RS (mais barata) | C126: 0.41 | D126: 0.41 | E126: 0.41 | F126: 2026-06-10 | G126: clarke.com.br
...

Sheet 4. Custos Fixos
A1: CUSTOS FIXOS MENSAIS — CLASSIFICAÇÃO
B2: Classificação: 🟢 OBRIGATÓRIO (não pode faltar) | 🟡 RECOMENDADO | ⚪ OPCIONAL
B4: Item | C4: Valor R$ | D4: Classe | E4: Observação / Fonte
B5: Pró-labore sócio 1 | C5: ='2. Premissas'!C7 | D5: 🟢 OBRIGATÓRIO | E5: Art. 1.071 IV CC; mínimo p/ sustentar Fator R do Anexo III
B6: Pró-labore sócio 2 | C6: ='2. Premissas'!C7 | D6: 🟢 OBRIGATÓRIO | E6: Idem
B7: INSS sócios (11% sobre pró-labore total) | C7: ='2. Premissas'!C11 | D7: 🟢 OBRIGATÓRIO | E7: Art. 21 Lei 8.212/91 (até teto RGPS)
B8: Internet empresarial (fibra) | C8: 200 | D8: 🟢 OBRIGATÓRIO | E8: Vivo R$ 128,98; TIM R$ 119-159; média R$ 100-180
B9: Energia adicional home office | C9: 80 | D9: 🟢 OBRIGATÓRIO | E9: Enel SP R$ 0,91/kWh × ~45 kWh/sócio
B10: Google Workspace (2 usuários) | C10: 65 | D10: 🟢 OBRIGATÓRIO | E10: R$ 32,72/user × 2 (anual)
B11: Contabilidade especializada | C11: 800 | D11: 🟢 OBRIGATÓRIO | E11: ME especializada R$ 700-1.200; Contabilizei online R$ 195
B12: Certificado Digital A1 | C12: 20 | D12: 🟢 OBRIGATÓRIO | E12: R$ 220/ano; necessário p/ NFS-e
B13: Hospedagem site Impulso + domínio | C13: 50 | D13: 🟢 OBRIGATÓRIO | E13: Hostinger + Registro.br R$ 40/ano
B14: Antivírus + backup nuvem | C14: 80 | D14: 🟢 OBRIGATÓRIO | E14: Segurança da operação
B15: ChatGPT Plus + Claude Pro (IA) | C15: 220 | D15: 🟡 RECOMENDADO | E15: US$ 20 × 2 ≈ R$ 108 × 2
B16: Figma Professional (2 editores anual) | C16: 162 | D16: 🟡 RECOMENDADO | E16: US$ 15 × 2 ≈ R$ 81 × 2
B17: Seguro RC profissional (E&O) | C17: 150 | D17: 🟡 RECOMENDADO | E17: Recomendação jurídica — limita responsabilidade civil
B18: Marketing próprio (mídia + ferramentas) | C18: 1200 | D18: 🟡 RECOMENDADO | E18: R$ 3-5k ideal; piso R$ 1.200
B19: Make / Zapier (automação) | C19: 60 | D19: 🟡 RECOMENDADO | E19: Make Core US$ 10,59
... B26: Slack Pro (2 users) | C26: 78 | D26: ⚪ OPCIONAL | E26: WhatsApp+Google Chat substituem no início
B28: TOTAL OBRIGATÓRIO | C28: =SUMIF(D5:D26,"🟢 OBRIGATÓRIO",C5:C26)
B29: TOTAL RECOMENDADO | C29: =SUMIF(D5:D26,"🟡 RECOMENDADO",C5:C26)
B30: TOTAL OPCIONAL | C30: =SUMIF(D5:D26,"⚪ OPCIONAL",C5:C26)
B31: CUSTO MENSAL TOTAL (todos) | C31: =SUM(C5:C26)
B33: CUSTO TOTAL ANUAL | C33: =SUM(C5:C26)*12

Sheet 5. Custos Variáveis
A1: CUSTOS VARIÁVEIS (% sobre receita ou por projeto)
B2: Valores em % são aplicados sobre receita; valores em R$ são por projeto/cliente
B4: Item | C4: Valor / % | D4: Observação / Fonte
B5: (% sobre receita) Imposto Simples Anexo III | C5: ='2. Premissas'!C31 | D5: Premissa editável — efetivo real: 6% até R$ 180k/ano
B6: (% sobre receita) Taxa de cartão MÉDIA | C6: ='2. Premissas'!C69 | D6: Média ponderada das modalidades
B7: (% sobre receita) Inadimplência (PCLD) | C7: ='2. Premissas'!C38 | D7: Conservador: 4% serviços B2B BR
B8: (% sobre receita) Comissão indicação (parcerias) | C8: 0.1 | D8: 10-20% se houver indicador externo
B9: (R$ por projeto) Plugins/apps Shopify específicos | C9: 200 | D9: Quando o pacote inclui app pago (estimativa média)
B10: (R$ por projeto) Templates pagos / temas premium | C10: 300 | D10: Tema Shopify premium US$ 200-350
B11: (R$ por projeto) Banco de imagens / fontes | C11: 100 | D11: Adobe Stock, Freepik PRO, etc.
B12: (R$ por projeto) Subcontratado eventual (designer/copy freela) | C12: 800 | D12: Quando o escopo exigir — opcional
B13: (R$ por mês) Tráfego pago próprio (aquisição clientes) | C13: 1500 | D13: Repassado da aba 4 marketing; também variável
B14: (R$ por hora extra de atendimento pós-venda) | C14: 89 | D14: Custo de oportunidade da hora produtiva
B15: Provisão para cancelamentos/devoluções | C15: 1-3% da receita | D15: Recomendação contábil (CPC 25 — Provisões)

Sheet 6. Capacidade
A1: CAPACIDADE OPERACIONAL — análise de horas
A3: HORAS DISPONÍVEIS (por mês)
B4: Linha | C4: Por sócio | D4: Total (2 sócios) | E4: % das brutas | F4: Observação
B5: Horas BRUTAS (22 dias × 8h) | C5: ='2. Premissas'!C16 | D5: ='2. Premissas'!C17 | E5: 100% | F5: Linha de partida
B6: (-) Comercial (pré-venda, propostas, reuniões) | C6: ='2. Premissas'!C17*0.15/'2. Premissas'!C5 | D6: ='2. Premissas'!C17*0.15 | E6: 15% | F6: 53h totais
B7: (-) Atendimento ativo + briefing | C7: ='2. Premissas'!C17*0.10/'2. Premissas'!C5 | D7: ='2. Premissas'!C17*0.10 | E7: 10% | F7: 35h totais
B8: (-) Pós-venda + suporte/garantia | C8: ='2. Premissas'!C17*0.10/'2. Premissas'!C5 | D8: ='2. Premissas'!C17*0.10 | E8: 10% | F8: 35h totais
B9: (-) Admin + financeiro + reuniões internas | C9: ='2. Premissas'!C17*0.08/'2. Premissas'!C5 | D9: ='2. Premissas'!C17*0.08 | E9: 8% | F9: 28h totais
B10: (-) Gestão + estudo + atualização templates | C10: ='2. Premissas'!C17*0.07/'2. Premissas'!C5 | D10: ='2. Premissas'!C17*0.07 | E10: 7% | F10: 25h totais
B11: =HORAS PRODUTIVAS de execução pura | C11: ='2. Premissas'!C19/'2. Premissas'!C5 | D11: ='2. Premissas'!C19 | E11: 50% | F11: Padrão de planejamento: 176h
B12: Capacidade ALVO sustentável (≤80%) | C12: ='2. Premissas'!C22/'2. Premissas'!C5 | D12: ='2. Premissas'!C22 | E12: 40% | F12: Operar ≤80% evita burnout
A14: MIX MENSAL RECOMENDADO (alvo ≤80% de capacidade)
B15: Combinação | C15: Start (20h) | D15: Pro (40h) | E15: Premium (70h) | F15: Horas totais | G15: Avaliação
B16: Volume máximo (NÃO recomendado) | C16: 4 | D16: 1 | E16: 0 | F16: =C16*20+D16*40+E16*70 | G16: ❌ 200h — estoura (>80%)
B17: Volume saudável | C17: 3 | D17: 1 | E17: 0 | F17: =C17*20+D17*40+E17*70 | G17: ✅ 100h — ok com folga
B18: Equilibrado | C18: 2 | D18: 1 | E18: 0 | F18: =C18*20+D18*40+E18*70 | G18: ✅ 80h — confortável
B19: Premium-foco | C19: 1 | D19: 0 | E19: 1 | F19: =C19*20+D19*40+E19*70 | G19: ✅ 90h — sustentável
B20: Target sustentável (recomendado) | C20: 2 | D20: 1 | E20: 0 | F20: =C20*20+D20*40+E20*70 | G20: ✅ 80h — pode adicionar suporte
B21: Premium puro (a cada 2 meses) | C21: 0 | D21: 0 | E21: 1 | F21: =C21*20+D21*40+E21*70 | G21: ✅ 70h — ok mas baixo throughput
A23: LIMITES DE SUPORTE RECORRENTE POR SÓCIO
B24: Plano | C24: Horas/mês cliente | D24: Capacidade nominal/sócio | E24: Teto operacional/sócio | F24: Mix sustentável
B25: Essencial (4h/mês) | C25: 4 | D25: 45 | E25: 25 | F25: Combinar com 1-2 Pro
B26: Profissional (10h/mês) | C26: 10 | D26: 18 | E26: 12 | F26: Limite mais comum
B27: Growth (20h/mês) | C27: 20 | D27: 9 | E27: 6 | F27: Cliente premium
A29: GATILHOS PARA CONTRATAR O 3º PROFISSIONAL
B30: ☐ Backlog vendido > 200h por 2 meses consecutivos
B31: ☐ Capacidade alocada > 85% por 2 meses
B32: ☐ Recusa de ≥2 projetos qualificados por mês por falta de slot
B33: ☐ Suporte recorrente > 50h/mês combinado
B34: ☐ NPS cai abaixo de 8 ou atraso médio > 20% sobre prazo prometido
B35: ☐ MRR ≥ R$ 20.000 por 3 meses (cobre custo de contratação CLT-flex ~R$ 6-9k all-in)
B36: ☐ Sócios trabalhando > 55h/semana ou rejeitando projetos por capacidade
B37: ✅ Perfil ideal da 1ª contratação: IMPLEMENTADOR PLENO em Shopify/Tray (não sênior). R$ 5-7k CLT-flex ou PJ. Sócios sobem para vendas + suporte estratégico + conteúdo.

Sheet 7. Preço 48 Horas
A1: PRECIFICAÇÃO — PROJETO 48 HORAS (3 pacotes)
B2: Fórmula de precificação: PV = (CustoHora × Horas) ÷ (1 - %Imposto - %TaxaMédia - %Inadimplência - %Margem)
A4: ESCOPO POR PACOTE
B5: Item | C5: START | D5: PRO | E5: PREMIUM | F5: Observação
B6: Plataformas suportadas | C6: Shopify, Nuvemshop, WP | D6: Shopify, Nuvemshop, Tray | E6: Shopify, Tray | F6: Woo só com +30%
B7: Limite de SKUs | C7: 15 | D7: 50 | E7: 150 | F7: Cadastro com fotos prontas
B8: Limite de páginas | C8: 5 | D8: 8 | E8: 12 | F8: Páginas institucionais
B9: Limite de integrações | C9: 1 | D9: 1 | E9: 2 | F9: Bling OU Tiny OU RD
B10: Limite de gateways | C10: 1 | D10: 2 | E10: 2 | F10: Aprovado antes do start
B11: Limite de modalidades de frete | C11: 1 | D11: 2 | E11: 2 | F11: Melhor Envio/Correios
B12: Reuniões inclusas | C12: 3 | D12: 3 | E12: 5 | F12: Briefing + validação + treinamento
B13: Sessões de treinamento (60min) | C13: 1 | D13: 2 | E13: 2 | F13: + videoteca de acesso
B14: Dias de suporte pós-go-live | C14: 7 | D14: 15 | E14: 30 | F14: Após, plano mensal obrigatório
B15: Horas humanas estimadas (mín) | C15: 22 | D15: 45 | E15: 90 | F15: Cenário ideal com pré-condições
B16: Horas humanas estimadas (esperada) | C16: 32 | D16: 70 | E16: 130 | F16: Mediana operacional
B17: Horas humanas estimadas (máx) | C17: 45 | D17: 100 | E17: 180 | F17: Cenário stress
A19: PRECIFICAÇÃO CALCULADA (base: horas esperadas)
B20: Linha | C20: START | D20: PRO | E20: PREMIUM | F20: Fórmula / Origem
B21: Custo interno (R$) | C21: ='2. Premissas'!C68*C16 | D21: ='2. Premissas'!C68*D16 | E21: ='2. Premissas'!C68*E16 | F21: =custo/h × horas
B22: PREÇO MÍNIMO (margem 20%) | C22: =('2. Premissas'!C68*C16)/(1-'2. Premissas'!C31-'2. Premissas'!C69-'2. Premissas'!C38-'2. Premissas'!C26) | D22: =('2. Premissas'!C68*D16)/(1-'2. Premissas'!C31-'2. Premissas'!C69-'2. Premissas'!C38-'2. Premissas'!C26) | E22: =('2. Premissas'!C68*E16)/(1-'2. Premissas'!C31-'2. Premissas'!C69-'2. Premissas'!C38-'2. Premissas'!C26) | F22: Custo / (1 - 12% - tx méd - 4% - 20%)
B23: PREÇO RECOMENDADO (margem 40%) | C23: =('2. Premissas'!C68*C16)/(1-'2. Premissas'!C31-'2. Premissas'!C69-'2. Premissas'!C38-'2. Premissas'!C27) | D23: =('2. Premissas'!C68*D16)/(1-'2. Premissas'!C31-'2. Premissas'!C69-'2. Premissas'!C38-'2. Premissas'!C27) | E23: =('2. Premissas'!C68*E16)/(1-'2. Premissas'!C31-'2. Premissas'!C69-'2. Premissas'!C38-'2. Premissas'!C27) | F23: Custo / (1 - 12% - tx méd - 4% - 40%)
B24: PREÇO PREMIUM (margem 55%) | C24: =('2. Premissas'!C68*C16)/(1-'2. Premissas'!C31-'2. Premissas'!C69-'2. Premissas'!C38-'2. Premissas'!C28) | D24: =('2. Premissas'!C68*D16)/(1-'2. Premissas'!C31-'2. Premissas'!C69-'2. Premissas'!C38-'2. Premissas'!C28) | E24: =('2. Premissas'!C68*E16)/(1-'2. Premissas'!C31-'2. Premissas'!C69-'2. Premissas'!C38-'2. Premissas'!C28) | F24: Custo / (1 - 12% - tx méd - 4% - 55%)
B25: PREÇO COMERCIAL SUGERIDO (ancoragem) | C25: 2490 | D25: 4990 | E25: 8900 | F25: Recomendação CFO: ancoragem + colchão p/ desconto
B26: Margem líquida no preço sugerido | C26: =1-'2. Premissas'!C31-'2. Premissas'!C69-'2. Premissas'!C38-(('2. Premissas'!C68*C16)/C25) | D26: =1-'2. Premissas'!C31-'2. Premissas'!C69-'2. Premissas'!C38-(('2. Premissas'!C68*D16)/D25) | E26: =1-'2. Premissas'!C31-'2. Premissas'!C69-'2. Premissas'!C38-(('2. Premissas'!C68*E16)/E25) | F26: =1 - imp - tx - inad - custo%
A28: SIMULAÇÃO POR MODALIDADE DE PAGAMENTO — Pacote PRO (preço sugerido)
B29: Modalidade | C29: Valor bruto | D29: Taxa % | E29: Taxa R$ | F29: Imposto R$ | G29: Líquido recebido
B30: PIX | C30: =D25 | D30: ='2. Premissas'!C32 | E30: =D25*'2. Premissas'!C32 | F30: =D25*'2. Premissas'!C31 | G30: =C30-E30-F30
B31: Cartão à vista | C31: =D25 | D31: ='2. Premissas'!C33 | E31: =D25*'2. Premissas'!C33 | F31: =D25*'2. Premissas'!C31 | G31: =C31-E31-F31
B32: Cartão 3x | C32: =D25 | D32: ='2. Premissas'!C34 | E32: =D25*'2. Premissas'!C34 | F32: =D25*'2. Premissas'!C31 | G32: =C32-E32-F32
B33: Cartão 6x | C33: =D25 | D33: ='2. Premissas'!C35 | E33: =D25*'2. Premissas'!C35 | F33: =D25*'2. Premissas'!C31 | G33: =C33-E33-F33
B34: Cartão 10x | C34: =D25 | D34: ='2. Premissas'!C36 | E34: =D25*'2. Premissas'!C36 | F34: =D25*'2. Premissas'!C31 | G34: =C34-E34-F34
B35: Cartão 12x | C35: =D25 | D35: ='2. Premissas'!C37 | E35: =D25*'2. Premissas'!C37 | F35: =D25*'2. Premissas'!C31 | G35: =C35-E35-F35
B37: 💡 POLÍTICA RECOMENDADA: 5% off PIX/à vista; máx 3x sem juros; 6x+ com juros repassados ao cliente. DNS sob domínio Impulso até pagamento final (50/40/10).

Sheet 8. Personalizados
A1: PRECIFICAÇÃO — PROJETOS PERSONALIZADOS
B2: Mesma fórmula: PV = (CustoHora × Horas) ÷ (1 - %Imp - %Tx - %Inad - %Margem)
A4: TABELA DE PROJETOS PERSONALIZADOS
B5: Projeto | C5: Horas estim. | D5: Custo interno | E5: Imposto | F5: Taxa cartão | G5: Preço MÍNIMO (20%) | H5: Preço RECOMENDADO (40%) | I5: Preço PREMIUM (55%)
B6: Site institucional simples (até 5 páginas) | C6: 30 | D6: ='2. Premissas'!C68*C6 | E6: =G6*'2. Premissas'!C31 | F6: =G6*'2. Premissas'!C69 | G6: =D6/(1-'2. Premissas'!C31-'2. Premissas'!C69-'2. Premissas'!C38-'2. Premissas'!C26) | H6: =D6/(1-'2. Premissas'!C31-'2. Premissas'!C69-'2. Premissas'!C38-'2. Premissas'!C27) | I6: =D6/(1-'2. Premissas'!C31-'2. Premissas'!C69-'2. Premissas'!C38-'2. Premissas'!C28)
B7: Site institucional premium (até 10 páginas + funil) | C7: 60 | D7: ='2. Premissas'!C68*C7 | E7: =G7*'2. Premissas'!C31 | F7: =G7*'2. Premissas'!C69 | G7: =D7/(1-'2. Premissas'!C31-'2. Premissas'!C69-'2. Premissas'!C38-'2. Premissas'!C26) | H7: =D7/(1-'2. Premissas'!C31-'2. Premissas'!C69-'2. Premissas'!C38-'2. Premissas'!C27) | I7: =D7/(1-'2. Premissas'!C31-'2. Premissas'!C69-'2. Premissas'!C38-'2. Premissas'!C28)
B8: Loja virtual personalizada (50-100 SKUs + integrações) | C8: 100 | D8: ='2. Premissas'!C68*C8 | E8: =G8*'2. Premissas'!C31 | F8: =G8*'2. Premissas'!C69 | G8: =D8/(1-'2. Premissas'!C31-'2. Premissas'!C69-'2. Premissas'!C38-'2. Premissas'!C26) | H8: =D8/(1-'2. Premissas'!C31-'2. Premissas'!C69-'2. Premissas'!C38-'2. Premissas'!C27) | I8: =D8/(1-'2. Premissas'!C31-'2. Premissas'!C69-'2. Premissas'!C38-'2. Premissas'!C28)
B9: Migração de plataforma (ex.: VTEX → Shopify) | C9: 80 | D9: ='2. Premissas'!C68*C9 | E9: =G9*'2. Premissas'!C31 | F9: =G9*'2. Premissas'!C69 | G9: =D9/(1-'2. Premissas'!C31-'2. Premissas'!C69-'2. Premissas'!C38-'2. Premissas'!C26) | H9: =D9/(1-'2. Premissas'!C31-'2. Premissas'!C69-'2. Premissas'!C38-'2. Premissas'!C27) | I9: =D9/(1-'2. Premissas'!C31-'2. Premissas'!C69-'2. Premissas'!C38-'2. Premissas'!C28)
B10: Integração com ERP (Bling/Tiny/Omie) | C10: 25 | D10: ='2. Premissas'!C68*C10 | E10: =G10*'2. Premissas'!C31 | F10: =G10*'2. Premissas'!C69 | G10: =D10/(1-'2. Premissas'!C31-'2. Premissas'!C69-'2. Premissas'!C38-'2. Premissas'!C26) | H10: =D10/(1-'2. Premissas'!C31-'2. Premissas'!C69-'2. Premissas'!C38-'2. Premissas'!C27) | I10: =D10/(1-'2. Premissas'!C31-'2. Premissas'!C69-'2. Premissas'!C38-'2. Premissas'!C28)
B11: Integração marketplace (ML/Amazon) por canal | C11: 30 | D11: ='2. Premissas'!C68*C11 | E11: =G11*'2. Premissas'!C31 | F11: =G11*'2. Premissas'!C69 | G11: =D11/(1-'2. Premissas'!C31-'2. Premissas'!C69-'2. Premissas'!C38-'2. Premissas'!C26) | H11: =D11/(1-'2. Premissas'!C31-'2. Premissas'!C69-'2. Premissas'!C38-'2. Premissas'!C27) | I11: =D11/(1-'2. Premissas'!C31-'2. Premissas'!C69-'2. Premissas'!C38-'2. Premissas'!C28)
B12: SEO técnico — projeto completo | C12: 40 | D12: ='2. Premissas'!C68*C12 | E12: =G12*'2. Premissas'!C31 | F12: =G12*'2. Premissas'!C69 | G12: =D12/(1-'2. Premissas'!C31-'2. Premissas'!C69-'2. Premissas'!C38-'2. Premissas'!C26) | H12: =D12/(1-'2. Premissas'!C31-'2. Premissas'!C69-'2. Premissas'!C38-'2. Premissas'!C27) | I12: =D12/(1-'2. Premissas'!C31-'2. Premissas'!C69-'2. Premissas'!C38-'2. Premissas'!C28)
B13: Automação comercial (RD/HubSpot/Klaviyo) | C13: 30 | D13: ='2. Premissas'!C68*C13 | E13: =G13*'2. Premissas'!C31 | F13: =G13*'2. Premissas'!C69 | G13: =D13/(1-'2. Premissas'!C31-'2. Premissas'!C69-'2. Premissas'!C38-'2. Premissas'!C26) | H13: =D13/(1-'2. Premissas'!C31-'2. Premissas'!C69-'2. Premissas'!C38-'2. Premissas'!C27) | I13: =D13/(1-'2. Premissas'!C31-'2. Premissas'!C69-'2. Premissas'!C38-'2. Premissas'!C28)
B14: CRM — setup + treinamento | C14: 25 | D14: ='2. Premissas'!C68*C14 | E14: =G14*'2. Premissas'!C31 | F14: =G14*'2. Premissas'!C69 | G14: =D14/(1-'2. Premissas'!C31-'2. Premissas'!C69-'2. Premissas'!C38-'2. Premissas'!C26) | H14: =D14/(1-'2. Premissas'!C31-'2. Premissas'!C69-'2. Premissas'!C38-'2. Premissas'!C27) | I14: =D14/(1-'2. Premissas'!C31-'2. Premissas'!C69-'2. Premissas'!C38-'2. Premissas'!C28)
B15: Landing page profissional (com funil + automação) | C15: 20 | D15: ='2. Premissas'!C68*C15 | E15: =G15*'2. Premissas'!C31 | F15: =G15*'2. Premissas'!C69 | G15: =D15/(1-'2. Premissas'!C31-'2. Premissas'!C69-'2. Premissas'!C38-'2. Premissas'!C26) | H15: =D15/(1-'2. Premissas'!C31-'2. Premissas'!C69-'2. Premissas'!C38-'2. Premissas'!C27) | I15: =D15/(1-'2. Premissas'!C31-'2. Premissas'!C69-'2. Premissas'!C38-'2. Premissas'!C28)
B16: Auditoria de e-commerce completa | C16: 18 | D16: ='2. Premissas'!C68*C16 | E16: =G16*'2. Premissas'!C31 | F16: =G16*'2. Premissas'!C69 | G16: =D16/(1-'2. Premissas'!C31-'2. Premissas'!C69-'2. Premissas'!C38-'2. Premissas'!C26) | H16: =D16/(1-'2. Premissas'!C31-'2. Premissas'!C69-'2. Premissas'!C38-'2. Premissas'!C27) | I16: =D16/(1-'2. Premissas'!C31-'2. Premissas'!C69-'2. Premissas'!C38-'2. Premissas'!C28)
B17: Consultoria estratégica (mensal, 1 sócio sênior) | C17: 20 | D17: ='2. Premissas'!C68*C17 | E17: =G17*'2. Premissas'!C31 | F17: =G17*'2. Premissas'!C69 | G17: =D17/(1-'2. Premissas'!C31-'2. Premissas'!C69-'2. Premissas'!C38-'2. Premissas'!C26) | H17: =D17/(1-'2. Premissas'!C31-'2. Premissas'!C69-'2. Premissas'!C38-'2. Premissas'!C27) | I17: =D17/(1-'2. Premissas'!C31-'2. Premissas'!C69-'2. Premissas'!C38-'2. Premissas'!C28)
B19: 📌 Para projetos personalizados: SEMPRE escopo fechado por escrito + change request formal para qualquer item adicional. Política de revisões: 2 rodadas estéticas; excedentes faturados por hora.

Sheet 9. Suporte
A1: PLANOS MENSAIS DE SUPORTE E MANUTENÇÃO
A3: 3 PLANOS RECORRENTES (MRR)
B4: Item | C4: ESSENCIAL | D4: PROFISSIONAL | E4: GROWTH
B5: Horas inclusas por mês | C5: 4 | D5: 10 | E5: 20
B6: Valor mensal sugerido (R$) | C6: 397 | D6: 990 | E6: 1890
B7: Custo interno (R$) | C7: ='2. Premissas'!C68*C5 | D7: ='2. Premissas'!C68*D5 | E7: ='2. Premissas'!C68*E5
B8: Imposto Simples (R$) | C8: =C6*'2. Premissas'!C31 | D8: =D6*'2. Premissas'!C31 | E8: =E6*'2. Premissas'!C31
B9: Margem líquida estimada | C9: =1-'2. Premissas'!C31-'2. Premissas'!C69-'2. Premissas'!C38-C7/C6 | D9: =1-'2. Premissas'!C31-'2. Premissas'!C69-'2. Premissas'!C38-D7/D6 | E9: =1-'2. Premissas'!C31-'2. Premissas'!C69-'2. Premissas'!C38-E7/E6
B10: SLA resposta (h úteis) | C10: 24 | D10: 8 | E10: 4
B11: SLA resolução P1 | C11: 5 d.u. | D11: 24 h | E11: 8 h
B12: Vigência mínima sugerida | C12: 6 meses | D12: 12 meses | E12: 12 meses
B13: Reajuste anual | C13: IPCA | D13: IPCA | E13: IPCA
B14: Limite nominal por sócio | C14: 45 clientes | D14: 18 clientes | E14: 9 clientes
B15: Teto operacional sustentável/sócio | C15: 25-30 | D15: 12-15 | E15: 6-8
B16: Itens INCLUSOS | C16: Ajustes técnicos pontuais; atualização de banners; pequenas correções; monitoramento básico (uptime, backup); atendimento consultivo por mensagem | D16: Tudo do Essencial + alterações em página existente (até 3/mês); ajuste de tema sem código; relatório mensal simples; revisão mensal por sócio | E16: Tudo do Profissional + 1 sprint de melhoria/mês; otimização de conversão pontual; revisão de SEO mensal; reunião quinzenal de planejamento
B17: Itens NÃO INCLUSOS (orçamento à parte) | C17: Customização de código; nova página; nova integração; redesign; produção de conteúdo | D17: Customização de código; redesign; produção de conteúdo extenso; gestão de tráfego pago | E17: Redesign completo; novas integrações > 1; produção de conteúdo extenso; gestão de tráfego pago (vendido à parte)
A19: ESTRATÉGIA DE RECORRÊNCIA (squad strategy)
B20: Meta: 50% conversão setup → suporte mensal em 12 meses; 65% em 24 meses. Mecânicas: 1) Bundle de saída: setup já inclui 30 dias de suporte cortesia + oferta de mensalidade 20% off se contratada em 7 dias. 2) Revisão de resultados D+30 e D+60 com sócio → mostra dados → abre upsell para Profissional/Growth. 3) Comunidade Impulso acessível apenas a clientes em recorrência (status premium). 4) SLA visível no contrato. Cláusula de upgrade/downgrade com 30 dias de aviso prévio. 5) Vigência mínima 12 meses (Pro/Growth) — válida B2B; em B2C, atenção CDC art. 51 IV (multa rescisória proporcional). RECEITA RECORRENTE É O CORAÇÃO DO NEGÓCIO. 1 R$ MRR vale 3-5× 1 R$ de projeto.

Sheet 10. Parceria
A1: RECEITA RECORRENTE DE PARCERIAS COM PLATAFORMAS
B2: Comissão de indicação — natureza jurídica: intermediação (LC 116/03 itens 10.02 / 17.12)
A4: PARÂMETROS DAS PLATAFORMAS PARCEIRAS
B5: Plataforma | C5: Mensalidade média cliente (R$) | D5: % Comissão Impulso | E5: Receita/cliente/mês | F5: Fonte
B6: Shopify Basic (US$ 29-39) | C6: 180 | D6: 0.2 | E6: =C6*D6 | F6: help.shopify.com/partners
B7: Shopify Grow (US$ 79-105) | C7: 500 | D7: 0.2 | E7: =C7*D7 | F7: shopify.com/pricing
B8: Tray (R$ 49-99 médio) | C8: 75 | D8: 0.2 | E8: =C8*D8 | F8: tray.com.br/partners
B9: Nuvemshop Essencial | C9: 59 | D9: 0.2 | E9: =C9*D9 | F9: atendimento.nuvemshop.com.br — comissões vigentes
B10: Nuvemshop Impulso (homônimo) | C10: 139 | D10: 0.2 | E10: =C10*D10 | F10: nuvemshop.com.br/planos-e-precos
B11: Nuvemshop Escala | C11: 389 | D11: 0.2 | E11: =C11*D11 | F11: nuvemshop.com.br/planos-e-precos
A13: SIMULAÇÃO DE RECEITA RECORRENTE — 3 CENÁRIOS
B14: Cenário | C14: Clientes mês 3 | D14: mês 6 | E14: mês 12 | F14: mês 24 | G14: MRR mês 12 (R$) | H14: Anual ano 1 (R$)
B15: Pessimista | C15: 2 | D15: 4 | E15: 8 | F15: 15 | G15: =E15*60 | H15: =((C15+E15)/2)*12*60
B16: Realista | C16: 3 | D16: 8 | E16: 18 | F16: 35 | G16: =E16*60 | H16: =((C16+E16)/2)*12*60
B17: Otimista | C17: 5 | D17: 12 | E17: 30 | F17: 60 | G17: =E17*60 | H17: =((C17+E17)/2)*12*60
B19: ⚠️ Premissas do squad: (1) Receita média/cliente assumida R$ 60/mês — mix de planos Tray + Nuvemshop Essencial + Shopify Basic. (2) Churn 3-5% a.m. esperado — incorporado no ramping. (3) Receita Shopify Partners é EXPORTAÇÃO de serviço (ISS isento art. 2º I LC 116/03; tributação só CPP+IRPJ+CSLL no DAS — art. 18 §14 LC 123/06). (4) Contrato de câmbio obrigatório (Lei 14.286/21). (5) Não receber verba de mídia em conta — cliente paga direto a Meta/Google.

Sheet 11. Tráfego Pago
A1: GESTÃO DE TRÁFEGO PAGO — MODELOS DE COBRANÇA
B2: ⚠️ Cliente paga MÍDIA direto Meta/Google (NÃO transitar pela Impulso). Impulso cobra apenas FEE de gestão.
A4: MATRIZ DE PRECIFICAÇÃO POR FAIXA DE VERBA DO CLIENTE
B5: Faixa de verba do cliente | C5: Setup (R$) | D5: Fee mensal (R$) | E5: Horas/mês | F5: % sobre verba | G5: Custo interno (R$) | H5: Margem
B6: Até R$ 2.000/mês mídia | C6: 800 | D6: 1200 | E6: 8 | F6: 10-15% | G6: ='2. Premissas'!C68*E6 | H6: =1-G6/D6-'2. Premissas'!C31-'2. Premissas'!C69
B7: R$ 2-5k mídia | C7: 1500 | D7: 2250 | E7: 12 | F7: 12-15% | G7: ='2. Premissas'!C68*E7 | H7: =1-G7/D7-'2. Premissas'!C31-'2. Premissas'!C69
B8: R$ 5-10k mídia | C8: 2500 | D8: 3750 | E8: 18 | F8: 10-15% | G8: ='2. Premissas'!C68*E8 | H8: =1-G8/D8-'2. Premissas'!C31-'2. Premissas'!C69
B9: >R$ 10k mídia | C9: 3500 | D9: 5000 | E9: 25 | F9: 10-12% | G9: ='2. Premissas'!C68*E9 | H9: =1-G9/D9-'2. Premissas'!C31-'2. Premissas'!C69
A11: MODELOS DE COBRANÇA — VANTAGENS E RISCOS
B12: Modelo | C12: Vantagens | D12: Riscos | E12: Quando usar
B13: Setup + Fee fixo mensal | C13: Previsibilidade total; alinhado a serviço, não a verba | D13: Cliente pode reduzir verba e exigir mesmo fee | E13: Recomendado p/ clientes pequenos
B14: % sobre verba (10-20%) | C14: Cresce com cliente; alinhado a investimento | D14: Variação do faturamento; risco se cliente cortar verba | E14: Cliente médio/grande
B15: Pacote híbrido (fee + %) | C15: Equilíbrio entre previsibilidade e upside | D15: Mais complexo de explicar | E15: MELHOR para clientes em escala
B16: Consultoria avulsa (hora) | C16: Margem alta em projetos pontuais | D16: Não escala; sem recorrência | E16: Auditorias + workshops
B18: ⚠️ Cláusula contratual obrigatória: 'A Impulso não garante volume, ROAS, CPA, faturamento ou ROI; tais resultados dependem de fatores externos (mercado, produto, preço, sazonalidade, política das plataformas).' (CDC art. 39 IV)

Sheet 12. Cenários
A1: CENÁRIOS FINANCEIROS — PROJEÇÃO 12 MESES
A4: CENÁRIO PESSIMISTA
B5: Linha | C5: M1 | D5: M2 | E5: M3 | F5: M4 | G5: M5 | H5: M6 | I5: M7 | J5: M8 | K5: M9 | L5: M10 | M5: M11 | N5: M12 | O5: Caixa final | P5: TOTAL ANO
B6: Receita Projeto 48h | C6: 3240 | D6: 3240 | E6: 3240 | F6: 6480 | G6: 6480 | H6: 6480 | I6: 6480 | J6: 9720 | K6: 9720 | L6: 9720 | M6: 9720 | N6: 9720 | P6: =SUM(C6:N6)
B7: Receita Personalizados | C7: 0 | D7: 0 | E7: 0 | F7: 0 | G7: 0 | H7: 0 | I7: 0 | J7: 0 | K7: 0 | L7: 0 | M7: 0 | N7: 0 | P7: 0
B8: Receita Suporte Mensal (acumulado) | C8: 0 | D8: 397 | E8: 794 | F8: 794 | G8: 1191 | H8: 1588 | I8: 1985 | J8: 2382 | K8: 2779 | L8: 3176 | M8: 3573 | N8: 3970 | P8: =SUM(C8:N8)
B9: Receita Parceria (acumulado) | C9: 0 | D9: 0 | E9: 0 | F9: 0 | G9: 0 | H9: 0 | I9: 60 | J9: 120 | K9: 180 | L9: 300 | M9: 420 | N9: 540 | P9: =SUM(C9:N9)
B10: Receita Tráfego Pago | C10: 0 | D10: 0 | E10: 0 | F10: 0 | G10: 0 | H10: 0 | I10: 0 | J10: 0 | K10: 0 | L10: 0 | M10: 0 | N10: 0 | P10: =SUM(C10:N10)
B11: RECEITA BRUTA TOTAL | C11: =SUM(C6:C10) | D11: =SUM(D6:D10) | E11: =SUM(E6:E10) | F11: =SUM(F6:F10) | G11: =SUM(G6:G10) | H11: =SUM(H6:H10) | I11: =SUM(I6:I10) | J11: =SUM(J6:J10) | ... N11: =SUM(N6:N10) | P11: =SUM(C11:N11)
B12: (-) Impostos (Simples 12%) | C12: =C11*'2. Premissas'!C31 | D12: =D11*'2. Premissas'!C31 | E12: =E11*'2. Premissas'!C31 | F12: =F11*'2. Premissas'!C31 | G12: =G11*'2. Premissas'!C31 | H12: =H11*'2. Premissas'!C31 | I12: =I11*'2. Premissas'!C31 | J12: =J11*'2. Premissas'!C31 | K12: =K11*'2. Premissas'!C31 | L12: =L11*'2. Premissas'!C31 | M12: =M11*'2. Premissas'!C31 | N12: =N11*'2. Premissas'!C31 | P12: =SUM(C12:N12)
B13: (-) Taxas cartão (média) | C13: =C11*'2. Premissas'!C69 | D13: =D11*'2. Premissas'!C69 | E13: =E11*'2. Premissas'!C69 | F13: =F11*'2. Premissas'!C69 | G13: =G11*'2. Premissas'!C69 | H13: =H11*'2. Premissas'!C69 | I13: =I11*'2. Premissas'!C69 | J13: =J11*'2. Premissas'!C69 | K13: =K11*'2. Premissas'!C69 | L13: =L11*'2. Premissas'!C69 | M13: =M11*'2. Premissas'!C69 | N13: =N11*'2. Premissas'!C69 | P13: =SUM(C13:N13)
B14: (-) Inadimplência (PCLD) | C14: =C11*'2. Premissas'!C38 | D14: =D11*'2. Premissas'!C38 | E14: =E11*'2. Premissas'!C38 | F14: =F11*'2. Premissas'!C38 | G14: =G11*'2. Premissas'!C38 | H14: =H11*'2. Premissas'!C38 | I14: =I11*'2. Premissas'!C38 | J14: =J11*'2. Premissas'!C38 | K14: =K11*'2. Premissas'!C38 | L14: =L11*'2. Premissas'!C38 | M14: =M11*'2. Premissas'!C38 | N14: =N11*'2. Premissas'!C38 | P14: =SUM(C14:N14)
B15: (-) Custos Fixos (sem pró-labore) | C15: ='2. Premissas'!C62 | D15: ='2. Premissas'!C62 | E15: ='2. Premissas'!C62 | F15: ='2. Premissas'!C62 | G15: ='2. Premissas'!C62 | H15: ='2. Premissas'!C62 | I15: ='2. Premissas'!C62 | J15: ='2. Premissas'!C62 | K15: ='2. Premissas'!C62 | L15: ='2. Premissas'!C62 | M15: ='2. Premissas'!C62 | N15: ='2. Premissas'!C62 | P15: =SUM(C15:N15)
B16: (-) Pró-labore + INSS sócios | C16: ='2. Premissas'!C9+'2. Premissas'!C11 | D16: ='2. Premissas'!C9+'2. Premissas'!C11 | E16: ='2. Premissas'!C9+'2. Premissas'!C11 | F16: ='2. Premissas'!C9+'2. Premissas'!C11 | G16: ='2. Premissas'!C9+'2. Premissas'!C11 | H16: ='2. Premissas'!C9+'2. Premissas'!C11 | I16: ='2. Premissas'!C9+'2. Premissas'!C11 | J16: ='2. Premissas'!C9+'2. Premissas'!C11 | K16: ='2. Premissas'!C9+'2. Premissas'!C11 | L16: ='2. Premissas'!C9+'2. Premissas'!C11 | M16: ='2. Premissas'!C9+'2. Premissas'!C11 | N16: ='2. Premissas'!C9+'2. Premissas'!C11 | P16: =SUM(C16:N16)
B17: LUCRO MENSAL | C17: =C11-C12-C13-C14-C15-C16 | D17: =D11-D12-D13-D14-D15-D16 | E17: =E11-E12-E13-E14-E15-E16 | F17: =F11-F12-F13-F14-F15-F16 | G17: =G11-G12-G13-G14-G15-G16 | H17: =H11-H12-H13-H14-H15-H16 | I17: =I11-I12-I13-I14-I15-I16 | J17: =J11-J12-J13-J14-J15-J16 | ... N17: =N11-N12-N13-N14-N15-N16 | P17: =SUM(C17:N17)
B18: Margem líquida % | C18: =IFERROR(C17/C11,0) | D18: =IFERROR(D17/D11,0) | E18: =IFERROR(E17/E11,0) | F18: =IFERROR(F17/F11,0) | G18: =IFERROR(G17/G11,0) | H18: =IFERROR(H17/H11,0) | I18: =IFERROR(I17/I11,0) | J18: =IFERROR(J17/J11,0) | ... N18: =IFERROR(N17/N11,0) | P18: =IFERROR(P17/P11,0)
B19: Caixa acumulado | C19: =C17 | D19: =C19+D17 | E19: =D19+E17 | F19: =E19+F17 | G19: =F19+G17 | H19: =G19+H17 | I19: =H19+I17 | J19: =I19+J17 | K19: =J19+K17 | ... N19: =M19+N17 | O19: =N19
B22: RESUMO ANUAL DO CENÁRIO
A31: CENÁRIO REALISTA
B32: Linha | C32: M1 | D32: M2 | E32: M3 | F32: M4 | G32: M5 | H32: M6 | I32: M7 | J32: M8 | K32: M9 | L32: M10 | M32: M11 | N32: M12 | O32: Caixa final | P32: TOTAL ANO
B33: Receita Projeto 48h | C33: 9544 | D33: 9544 | E33: 14316 | F33: 14316 | G33: 14316 | H33: 14316 | I33: 14316 | J33: 14316 | K33: 14316 | L33: 14316 | M33: 14316 | N33: 14316 | P33: =SUM(C33:N33)
B34: Receita Personalizados | C34: 0 | D34: 0 | E34: 0 | F34: 0 | G34: 0 | H34: 0 | I34: 0 | J34: 0 | K34: 0 | L34: 0 | M34: 0 | N34: 0 | P34: 0
B35: Receita Suporte Mensal (acumulado) | C35: 990 | D35: 2970 | E35: 4950 | F35: 6930 | G35: 8910 | H35: 10890 | I35: 12870 | J35: 14850 | K35: 16830 | L35: 18810 | M35: 20790 | N35: 22770 | P35: =SUM(C35:N35)
B36: Receita Parceria (acumulado) | C36: 0 | D36: 0 | E36: 60 | F36: 120 | G36: 240 | H36: 360 | I36: 480 | J36: 600 | K36: 720 | L36: 840 | M36: 960 | N36: 1080 | P36: =SUM(C36:N36)
B37: Receita Tráfego Pago | C37: 0 | D37: 0 | E37: 0 | F37: 2500 | G37: 2500 | H37: 2500 | I37: 2500 | J37: 2500 | K37: 2500 | L37: 2500 | M37: 2500 | N37: 2500 | P37: =SUM(C37:N37)
B38: RECEITA BRUTA TOTAL | C38: =SUM(C33:C37) | D38: =SUM(D33:D37) | E38: =SUM(E33:E37) | F38: =SUM(F33:F37) | G38: =SUM(G33:G37) | H38: =SUM(H33:H37) | I38: =SUM(I33:I37) | J38: =SUM(J33:J37) | ... N38: =SUM(N33:N37) | P38: =SUM(C38:N38)
B39: (-) Impostos (Simples 12%) | C39: =C38*'2. Premissas'!C31 | D39: =D38*'2. Premissas'!C31 | E39: =E38*'2. Premissas'!C31 | F39: =F38*'2. Premissas'!C31 | G39: =G38*'2. Premissas'!C31 | H39: =H38*'2. Premissas'!C31 | I39: =I38*'2. Premissas'!C31 | J39: =J38*'2. Premissas'!C31 | K39: =K38*'2. Premissas'!C31 | L39: =L38*'2. Premissas'!C31 | M39: =M38*'2. Premissas'!C31 | N39: =N38*'2. Premissas'!C31 | P39: =SUM(C39:N39)
B40: (-) Taxas cartão (média) | C40: =C38*'2. Premissas'!C69 | D40: =D38*'2. Premissas'!C69 | E40: =E38*'2. Premissas'!C69 | F40: =F38*'2. Premissas'!C69 | G40: =G38*'2. Premissas'!C69 | H40: =H38*'2. Premissas'!C69 | I40: =I38*'2. Premissas'!C69 | J40: =J38*'2. Premissas'!C69 | K40: =K38*'2. Premissas'!C69 | L40: =L38*'2. Premissas'!C69 | M40: =M38*'2. Premissas'!C69 | N40: =N38*'2. Premissas'!C69 | P40: =SUM(C40:N40)
B41: (-) Inadimplência (PCLD) | C41: =C38*'2. Premissas'!C38 | D41: =D38*'2. Premissas'!C38 | E41: =E38*'2. Premissas'!C38 | F41: =F38*'2. Premissas'!C38 | G41: =G38*'2. Premissas'!C38 | H41: =H38*'2. Premissas'!C38 | I41: =I38*'2. Premissas'!C38 | J41: =J38*'2. Premissas'!C38 | K41: =K38*'2. Premissas'!C38 | L41: =L38*'2. Premissas'!C38 | M41: =M38*'2. Premissas'!C38 | N41: =N38*'2. Premissas'!C38 | P41: =SUM(C41:N41)
B42: (-) Custos Fixos (sem pró-labore) | C42: ='2. Premissas'!C62 | D42: ='2. Premissas'!C62 | E42: ='2. Premissas'!C62 | F42: ='2. Premissas'!C62 | G42: ='2. Premissas'!C62 | H42: ='2. Premissas'!C62 | I42: ='2. Premissas'!C62 | J42: ='2. Premissas'!C62 | K42: ='2. Premissas'!C62 | L42: ='2. Premissas'!C62 | M42: ='2. Premissas'!C62 | N42: ='2. Premissas'!C62 | P42: =SUM(C42:N42)
B43: (-) Pró-labore + INSS sócios | C43: ='2. Premissas'!C9+'2. Premissas'!C11 | D43: ='2. Premissas'!C9+'2. Premissas'!C11 | E43: ='2. Premissas'!C9+'2. Premissas'!C11 | F43: ='2. Premissas'!C9+'2. Premissas'!C11 | G43: ='2. Premissas'!C9+'2. Premissas'!C11 | H43: ='2. Premissas'!C9+'2. Premissas'!C11 | I43: ='2. Premissas'!C9+'2. Premissas'!C11 | J43: ='2. Premissas'!C9+'2. Premissas'!C11 | K43: ='2. Premissas'!C9+'2. Premissas'!C11 | L43: ='2. Premissas'!C9+'2. Premissas'!C11 | M43: ='2. Premissas'!C9+'2. Premissas'!C11 | N43: ='2. Premissas'!C9+'2. Premissas'!C11 | P43: =SUM(C43:N43)
B44: LUCRO MENSAL | C44: =C38-C39-C40-C41-C42-C43 | D44: =D38-D39-D40-D41-D42-D43 | E44: =E38-E39-E40-E41-E42-E43 | F44: =F38-F39-F40-F41-F42-F43 | G44: =G38-G39-G40-G41-G42-G43 | H44: =H38-H39-H40-H41-H42-H43 | I44: =I38-I39-I40-I41-I42-I43 | J44: =J38-J39-J40-J41-J42-J43 | ... N44: =N38-N39-N40-N41-N42-N43 | P44: =SUM(C44:N44)
B45: Margem líquida % | C45: =IFERROR(C44/C38,0) | D45: =IFERROR(D44/D38,0) | E45: =IFERROR(E44/E38,0) | F45: =IFERROR(F44/F38,0) | G45: =IFERROR(G44/G38,0) | H45: =IFERROR(H44/H38,0) | I45: =IFERROR(I44/I38,0) | J45: =IFERROR(J44/J38,0) | ... N45: =IFERROR(N44/N38,0) | P45: =IFERROR(P44/P38,0)
B46: Caixa acumulado | C46: =C44 | D46: =C46+D44 | E46: =D46+E44 | F46: =E46+F44 | G46: =F46+G44 | H46: =G46+H44 | I46: =H46+I44 | J46: =I46+J44 | K46: =J46+K44 | ... N46: =M46+N44 | O46: =N46
B49: RESUMO ANUAL DO CENÁRIO
A58: CENÁRIO OTIMISTA
B59: Linha | C59: M1 | D59: M2 | E59: M3 | F59: M4 | G59: M5 | H59: M6 | I59: M7 | J59: M8 | K59: M9 | L59: M10 | M59: M11 | N59: M12 | O59: Caixa final | P59: TOTAL ANO
B60: Receita Projeto 48h | C60: 15066 | D60: 20088 | E60: 20088 | F60: 25110 | G60: 25110 | H60: 25110 | I60: 25110 | J60: 25110 | K60: 25110 | L60: 25110 | M60: 25110 | N60: 25110 | P60: =SUM(C60:N60)
B61: Receita Personalizados | C61: 0 | D61: 0 | E61: 0 | F61: 0 | G61: 0 | H61: 0 | I61: 0 | J61: 0 | K61: 0 | L61: 0 | M61: 0 | N61: 0 | P61: 0
B62: Receita Suporte Mensal (acumulado) | C62: 1980 | D62: 4950 | E62: 7920 | F62: 10890 | G62: 13860 | H62: 16830 | I62: 19800 | J62: 22770 | K62: 25740 | L62: 28710 | M62: 31680 | N62: 34650 | P62: =SUM(C62:N62)
B63: Receita Parceria (acumulado) | C63: 60 | D63: 180 | E63: 300 | F63: 480 | G63: 660 | H63: 840 | I63: 1020 | J63: 1200 | K63: 1380 | L63: 1560 | M63: 1740 | N63: 1920 | P63: =SUM(C63:N63)
B64: Receita Tráfego Pago | C64: 2500 | D64: 2500 | E64: 5000 | F64: 5000 | G64: 5000 | H64: 5000 | I64: 5000 | J64: 5000 | K64: 5000 | L64: 5000 | M64: 5000 | N64: 5000 | P64: =SUM(C64:N64)
B65: RECEITA BRUTA TOTAL | C65: =SUM(C60:C64) | D65: =SUM(D60:D64) | E65: =SUM(E60:E64) | F65: =SUM(F60:F64) | G65: =SUM(G60:G64) | H65: =SUM(H60:H64) | I65: =SUM(I60:I64) | J65: =SUM(J60:J64) | ... N65: =SUM(N60:N64) | P65: =SUM(C65:N65)
B66: (-) Impostos (Simples 12%) | C66: =C65*'2. Premissas'!C31 | D66: =D65*'2. Premissas'!C31 | E66: =E65*'2. Premissas'!C31 | F66: =F65*'2. Premissas'!C31 | G66: =G65*'2. Premissas'!C31 | H66: =H65*'2. Premissas'!C31 | I66: =I65*'2. Premissas'!C31 | J66: =J65*'2. Premissas'!C31 | K66: =K65*'2. Premissas'!C31 | L66: =L65*'2. Premissas'!C31 | M66: =M65*'2. Premissas'!C31 | N66: =N65*'2. Premissas'!C31 | P66: =SUM(C66:N66)
B67: (-) Taxas cartão (média) | C67: =C65*'2. Premissas'!C69 | D67: =D65*'2. Premissas'!C69 | E67: =E65*'2. Premissas'!C69 | F67: =F65*'2. Premissas'!C69 | G67: =G65*'2. Premissas'!C69 | H67: =H65*'2. Premissas'!C69 | I67: =I65*'2. Premissas'!C69 | J67: =J65*'2. Premissas'!C69 | K67: =K65*'2. Premissas'!C69 | L67: =L65*'2. Premissas'!C69 | M67: =M65*'2. Premissas'!C69 | N67: =N65*'2. Premissas'!C69 | P67: =SUM(C67:N67)
B68: (-) Inadimplência (PCLD) | C68: =C65*'2. Premissas'!C38 | D68: =D65*'2. Premissas'!C38 | E68: =E65*'2. Premissas'!C38 | F68: =F65*'2. Premissas'!C38 | G68: =G65*'2. Premissas'!C38 | H68: =H65*'2. Premissas'!C38 | I68: =I65*'2. Premissas'!C38 | J68: =J65*'2. Premissas'!C38 | K68: =K65*'2. Premissas'!C38 | L68: =L65*'2. Premissas'!C38 | M68: =M65*'2. Premissas'!C38 | N68: =N65*'2. Premissas'!C38 | P68: =SUM(C68:N68)
B69: (-) Custos Fixos (sem pró-labore) | C69: ='2. Premissas'!C62 | D69: ='2. Premissas'!C62 | E69: ='2. Premissas'!C62 | F69: ='2. Premissas'!C62 | G69: ='2. Premissas'!C62 | H69: ='2. Premissas'!C62 | I69: ='2. Premissas'!C62 | J69: ='2. Premissas'!C62 | K69: ='2. Premissas'!C62 | L69: ='2. Premissas'!C62 | M69: ='2. Premissas'!C62 | N69: ='2. Premissas'!C62 | P69: =SUM(C69:N69)
B70: (-) Pró-labore + INSS sócios | C70: ='2. Premissas'!C9+'2. Premissas'!C11 | D70: ='2. Premissas'!C9+'2. Premissas'!C11 | E70: ='2. Premissas'!C9+'2. Premissas'!C11 | F70: ='2. Premissas'!C9+'2. Premissas'!C11 | G70: ='2. Premissas'!C9+'2. Premissas'!C11 | H70: ='2. Premissas'!C9+'2. Premissas'!C11 | I70: ='2. Premissas'!C9+'2. Premissas'!C11 | J70: ='2. Premissas'!C9+'2. Premissas'!C11 | K70: ='2. Premissas'!C9+'2. Premissas'!C11 | L70: ='2. Premissas'!C9+'2. Premissas'!C11 | M70: ='2. Premissas'!C9+'2. Premissas'!C11 | N70: ='2. Premissas'!C9+'2. Premissas'!C11 | P70: =SUM(C70:N70)
B71: LUCRO MENSAL | C71: =C65-C66-C67-C68-C69-C70 | D71: =D65-D66-D67-D68-D69-D70 | E71: =E65-E66-E67-E68-E69-E70 | F71: =F65-F66-F67-F68-F69-F70 | G71: =G65-G66-G67-G68-G69-G70 | H71: =H65-H66-H67-H68-H69-H70 | I71: =I65-I66-I67-I68-I69-I70 | J71: =J65-J66-J67-J68-J69-J70 | ... N71: =N65-N66-N67-N68-N69-N70 | P71: =SUM(C71:N71)
B72: Margem líquida % | C72: =IFERROR(C71/C65,0) | D72: =IFERROR(D71/D65,0) | E72: =IFERROR(E71/E65,0) | F72: =IFERROR(F71/F65,0) | G72: =IFERROR(G71/G65,0) | H72: =IFERROR(H71/H65,0) | I72: =IFERROR(I71/I65,0) | J72: =IFERROR(J71/J65,0) | ... N72: =IFERROR(N71/N65,0) | P72: =IFERROR(P71/P65,0)
B73: Caixa acumulado | C73: =C71 | D73: =C73+D71 | E73: =D73+E71 | F73: =E73+F71 | G73: =F73+G71 | H73: =G73+H71 | I73: =H73+I71 | J73: =I73+J71 | K73: =J73+K71 | ... N73: =M73+N71 | O73: =N73
B76: RESUMO ANUAL DO CENÁRIO
B80: 📊 RESUMO ANUAL COMPARATIVO (linkado à aba 1)
B81: Indicador | C81: Pessimista | D81: Realista | E81: Otimista
B82: Receita bruta anual | C82: =P11 | D82: =P38 | E82: =P65
B83: Lucro líquido anual | C83: =P17 | D83: =P44 | E83: =P71
B84: Margem líquida média | C84: =P18 | D84: =P45 | E84: =P72
B85: Caixa acumulado final mês 12 | C85: =O19 | D85: =O46 | E85: =O73

Sheet 13. DRE
A1: DRE PROJETADA — CENÁRIO REALISTA (12 meses)
B2: Estrutura conforme CPC 26 (R1). Vinculada à aba 12 — Realista (linhas 31-48)
B4: Linha DRE | C4: M1 | D4: M2 | E4: M3 | F4: M4 | G4: M5 | H4: M6 | I4: M7 | J4: M8 | K4: M9 | L4: M10 | M4: M11 | N4: M12 | O4: ANO
B5: RECEITA BRUTA OPERACIONAL | C5: ='12. Cenários'!C38 | D5: ='12. Cenários'!D38 | E5: ='12. Cenários'!E38 | F5: ='12. Cenários'!F38 | G5: ='12. Cenários'!G38 | H5: ='12. Cenários'!H38 | I5: ='12. Cenários'!I38 | J5: ='12. Cenários'!J38 | ... N5: ='12. Cenários'!N38 | O5: ='12. Cenários'!P38
B6: Projeto 48 Horas | C6: ='12. Cenários'!C33 | D6: ='12. Cenários'!D33 | E6: ='12. Cenários'!E33 | F6: ='12. Cenários'!F33 | G6: ='12. Cenários'!G33 | H6: ='12. Cenários'!H33 | I6: ='12. Cenários'!I33 | J6: ='12. Cenários'!J33 | ... N6: ='12. Cenários'!N33 | O6: ='12. Cenários'!P33
B7: Projetos Personalizados | C7: ='12. Cenários'!C34 | D7: ='12. Cenários'!D34 | E7: ='12. Cenários'!E34 | F7: ='12. Cenários'!F34 | G7: ='12. Cenários'!G34 | H7: ='12. Cenários'!H34 | I7: ='12. Cenários'!I34 | J7: ='12. Cenários'!J34 | ... N7: ='12. Cenários'!N34 | O7: ='12. Cenários'!P34
B8: Suporte Mensal Recorrente (MRR) | C8: ='12. Cenários'!C35 | D8: ='12. Cenários'!D35 | E8: ='12. Cenários'!E35 | F8: ='12. Cenários'!F35 | G8: ='12. Cenários'!G35 | H8: ='12. Cenários'!H35 | I8: ='12. Cenários'!I35 | J8: ='12. Cenários'!J35 | ... N8: ='12. Cenários'!N35 | O8: ='12. Cenários'!P35
B9: Parceria com Plataformas | C9: ='12. Cenários'!C36 | D9: ='12. Cenários'!D36 | E9: ='12. Cenários'!E36 | F9: ='12. Cenários'!F36 | G9: ='12. Cenários'!G36 | H9: ='12. Cenários'!H36 | I9: ='12. Cenários'!I36 | J9: ='12. Cenários'!J36 | ... N9: ='12. Cenários'!N36 | O9: ='12. Cenários'!P36
B10: Tráfego Pago (gestão) | C10: ='12. Cenários'!C37 | D10: ='12. Cenários'!D37 | E10: ='12. Cenários'!E37 | F10: ='12. Cenários'!F37 | G10: ='12. Cenários'!G37 | H10: ='12. Cenários'!H37 | I10: ='12. Cenários'!I37 | J10: ='12. Cenários'!J37 | ... N10: ='12. Cenários'!N37 | O10: ='12. Cenários'!P37
B11: (–) Impostos sobre venda (Simples) | C11: ='12. Cenários'!C39 | D11: ='12. Cenários'!D39 | E11: ='12. Cenários'!E39 | F11: ='12. Cenários'!F39 | G11: ='12. Cenários'!G39 | H11: ='12. Cenários'!H39 | I11: ='12. Cenários'!I39 | J11: ='12. Cenários'!J39 | ... N11: ='12. Cenários'!N39 | O11: ='12. Cenários'!P39
B12: (–) Taxas de cartão | C12: ='12. Cenários'!C40 | D12: ='12. Cenários'!D40 | E12: ='12. Cenários'!E40 | F12: ='12. Cenários'!F40 | G12: ='12. Cenários'!G40 | H12: ='12. Cenários'!H40 | I12: ='12. Cenários'!I40 | J12: ='12. Cenários'!J40 | ... N12: ='12. Cenários'!N40 | O12: ='12. Cenários'!P40
B13: (–) Inadimplência (PCLD) | C13: ='12. Cenários'!C41 | D13: ='12. Cenários'!D41 | E13: ='12. Cenários'!E41 | F13: ='12. Cenários'!F41 | G13: ='12. Cenários'!G41 | H13: ='12. Cenários'!H41 | I13: ='12. Cenários'!I41 | J13: ='12. Cenários'!J41 | ... N13: ='12. Cenários'!N41 | O13: ='12. Cenários'!P41
B14: =RECEITA LÍQUIDA | C14: ='12. Cenários'!C38 - '12. Cenários'!C39 - '12. Cenários'!C40 - '12. Cenários'!C41 | D14: ='12. Cenários'!D38 - '12. Cenários'!D39 - '12. Cenários'!D40 - '12. Cenários'!D41 | E14: ='12. Cenários'!E38 - '12. Cenários'!E39 - '12. Cenários'!E40 - '12. Cenários'!E41 | F14: ='12. Cenários'!F38 - '12. Cenários'!F39 - '12. Cenários'!F40 - '12. Cenários'!F41 | G14: ='12. Cenários'!G38 - '12. Cenários'!G39 - '12. Cenários'!G40 - '12. Cenários'!G41 | H14: ='12. Cenários'!H38 - '12. Cenários'!H39 - '12. Cenários'!H40 - '12. Cenários'!H41 | I14: ='12. Cenários'!I38 - '12. Cenários'!I39 - '12. Cenários'!I40 - '12. Cenários'!I41 | J14: ='12. Cenários'!J38 - '12. Cenários'!J39 - '12. Cenários'!J40 - '12. Cenários'!J41 | ... N14: ='12. Cenários'!N38 - '12. Cenários'!N39 - '12. Cenários'!N40 - '12. Cenários'!N41 | O14: ='12. Cenários'!P38 - '12. Cenários'!P39 - '12. Cenários'!P40 - '12. Cenários'!P41
B15: (–) Custos Fixos Administrativos | C15: ='12. Cenários'!C42 | D15: ='12. Cenários'!D42 | E15: ='12. Cenários'!E42 | F15: ='12. Cenários'!F42 | G15: ='12. Cenários'!G42 | H15: ='12. Cenários'!H42 | I15: ='12. Cenários'!I42 | J15: ='12. Cenários'!J42 | ... N15: ='12. Cenários'!N42 | O15: ='12. Cenários'!P42
B16: (–) Pró-labore + INSS sócios | C16: ='12. Cenários'!C43 | D16: ='12. Cenários'!D43 | E16: ='12. Cenários'!E43 | F16: ='12. Cenários'!F43 | G16: ='12. Cenários'!G43 | H16: ='12. Cenários'!H43 | I16: ='12. Cenários'!I43 | J16: ='12. Cenários'!J43 | ... N16: ='12. Cenários'!N43 | O16: ='12. Cenários'!P43
B17: =LUCRO LÍQUIDO MENSAL | C17: ='12. Cenários'!C44 | D17: ='12. Cenários'!D44 | E17: ='12. Cenários'!E44 | F17: ='12. Cenários'!F44 | G17: ='12. Cenários'!G44 | H17: ='12. Cenários'!H44 | I17: ='12. Cenários'!I44 | J17: ='12. Cenários'!J44 | ... N17: ='12. Cenários'!N44 | O17: ='12. Cenários'!P44
B18: Margem líquida (%) | C18: =IFERROR('12. Cenários'!C44/'12. Cenários'!C38,0) | D18: =IFERROR('12. Cenários'!D44/'12. Cenários'!D38,0) | E18: =IFERROR('12. Cenários'!E44/'12. Cenários'!E38,0) | F18: =IFERROR('12. Cenários'!F44/'12. Cenários'!F38,0) | G18: =IFERROR('12. Cenários'!G44/'12. Cenários'!G38,0) | H18: =IFERROR('12. Cenários'!H44/'12. Cenários'!H38,0) | I18: =IFERROR('12. Cenários'!I44/'12. Cenários'!I38,0) | J18: =IFERROR('12. Cenários'!J44/'12. Cenários'!J38,0) | ... N18: =IFERROR('12. Cenários'!N44/'12. Cenários'!N38,0) | O18: =IFERROR('12. Cenários'!P44/'12. Cenários'!P38,0)

Sheet 14. Fluxo de Caixa
A1: FLUXO DE CAIXA — CENÁRIO REALISTA (12 meses)
B2: Considera descasamento entre receita reconhecida e caixa efetivamente recebido (parcelamento)
B4: Movimento | C4: M1 | D4: M2 | E4: M3 | F4: M4 | G4: M5 | H4: M6 | I4: M7 | J4: M8 | K4: M9 | L4: M10 | M4: M11 | N4: M12 | O4: ANO
B5: (+) Recebimentos à vista/PIX (60% da receita) | C5: ='12. Cenários'!C38*0.6 | D5: ='12. Cenários'!D38*0.6 | E5: ='12. Cenários'!E38*0.6 | F5: ='12. Cenários'!F38*0.6 | G5: ='12. Cenários'!G38*0.6 | H5: ='12. Cenários'!H38*0.6 | I5: ='12. Cenários'!I38*0.6 | J5: ='12. Cenários'!J38*0.6 | ... N5: ='12. Cenários'!N38*0.6 | O5: =SUM(C5:N5)
B6: (+) Recebimentos parcelado 3x (30% receita, diluído em 3 meses) | C6: ='12. Cenários'!C38*0.3 | D6: ='12. Cenários'!D38*0.3 | E6: ='12. Cenários'!E38*0.3 | F6: ='12. Cenários'!F38*0.3 | G6: ='12. Cenários'!G38*0.3 | H6: ='12. Cenários'!H38*0.3 | I6: ='12. Cenários'!I38*0.3 | J6: ='12. Cenários'!J38*0.3 | ... N6: ='12. Cenários'!N38*0.3 | O6: =SUM(C6:N6)
B7: (+) Recebimentos parcelado 6x+ (10% receita) | C7: ='12. Cenários'!C38*0.1 | D7: ='12. Cenários'!D38*0.1 | E7: ='12. Cenários'!E38*0.1 | F7: ='12. Cenários'!F38*0.1 | G7: ='12. Cenários'!G38*0.1 | H7: ='12. Cenários'!H38*0.1 | I7: ='12. Cenários'!I38*0.1 | J7: ='12. Cenários'!J38*0.1 | ... N7: ='12. Cenários'!N38*0.1 | O7: =SUM(C7:N7)
B8: =TOTAL ENTRADAS | C8: =SUM(C5:C7) | D8: =SUM(D5:D7) | E8: =SUM(E5:E7) | F8: =SUM(F5:F7) | G8: =SUM(G5:G7) | H8: =SUM(H5:H7) | I8: =SUM(I5:I7) | J8: =SUM(J5:J7) | ... N8: =SUM(N5:N7) | O8: =SUM(C8:N8)
B10: (–) Impostos (Simples) | C10: ='12. Cenários'!C39 | D10: ='12. Cenários'!D39 | E10: ='12. Cenários'!E39 | F10: ='12. Cenários'!F39 | G10: ='12. Cenários'!G39 | H10: ='12. Cenários'!H39 | I10: ='12. Cenários'!I39 | J10: ='12. Cenários'!J39 | ... N10: ='12. Cenários'!N39 | O10: =SUM(C10:N10)
B11: (–) Taxas cartão | C11: ='12. Cenários'!C40 | D11: ='12. Cenários'!D40 | E11: ='12. Cenários'!E40 | F11: ='12. Cenários'!F40 | G11: ='12. Cenários'!G40 | H11: ='12. Cenários'!H40 | I11: ='12. Cenários'!I40 | J11: ='12. Cenários'!J40 | ... N11: ='12. Cenários'!N40 | O11: =SUM(C11:N11)
B12: (–) Inadimplência (PCLD) | C12: ='12. Cenários'!C41 | D12: ='12. Cenários'!D41 | E12: ='12. Cenários'!E41 | F12: ='12. Cenários'!F41 | G12: ='12. Cenários'!G41 | H12: ='12. Cenários'!H41 | I12: ='12. Cenários'!I41 | J12: ='12. Cenários'!J41 | ... N12: ='12. Cenários'!N41 | O12: =SUM(C12:N12)
B13: (–) Custos fixos administrativos | C13: ='2. Premissas'!C62 | D13: ='2. Premissas'!C62 | E13: ='2. Premissas'!C62 | F13: ='2. Premissas'!C62 | G13: ='2. Premissas'!C62 | H13: ='2. Premissas'!C62 | I13: ='2. Premissas'!C62 | J13: ='2. Premissas'!C62 | K13: ='2. Premissas'!C62 | L13: ='2. Premissas'!C62 | M13: ='2. Premissas'!C62 | N13: ='2. Premissas'!C62 | O13: =SUM(C13:N13)
B14: (–) Pró-labore + INSS sócios | C14: ='2. Premissas'!C9+'2. Premissas'!C11 | D14: ='2. Premissas'!C9+'2. Premissas'!C11 | E14: ='2. Premissas'!C9+'2. Premissas'!C11 | F14: ='2. Premissas'!C9+'2. Premissas'!C11 | G14: ='2. Premissas'!C9+'2. Premissas'!C11 | H14: ='2. Premissas'!C9+'2. Premissas'!C11 | I14: ='2. Premissas'!C9+'2. Premissas'!C11 | J14: ='2. Premissas'!C9+'2. Premissas'!C11 | K14: ='2. Premissas'!C9+'2. Premissas'!C11 | L14: ='2. Premissas'!C9+'2. Premissas'!C11 | M14: ='2. Premissas'!C9+'2. Premissas'!C11 | N14: ='2. Premissas'!C9+'2. Premissas'!C11 | O14: =SUM(C14:N14)
B15: =TOTAL SAÍDAS | C15: =C10+C11+C12+C13+C14 | D15: =D10+D11+D12+D13+D14 | E15: =E10+E11+E12+E13+E14 | F15: =F10+F11+F12+F13+F14 | G15: =G10+G11+G12+G13+G14 | H15: =H10+H11+H12+H13+H14 | I15: =I10+I11+I12+I13+I14 | J15: =J10+J11+J12+J13+J14 | ... N15: =N10+N11+N12+N13+N14 | O15: =SUM(C15:N15)
B17: =FLUXO DE CAIXA DO MÊS | C17: =C8-C15 | D17: =D8-D15 | E17: =E8-E15 | F17: =F8-F15 | G17: =G8-G15 | H17: =H8-H15 | I17: =I8-I15 | J17: =J8-J15 | ... N17: =N8-N15 | O17: =SUM(C17:N17)
B18: (+) Caixa inicial (reserva) | C18: 50000 | D18: =C19 | E18: =D19 | F18: =E19 | G18: =F19 | H18: =G19 | I18: =H19 | J18: =I19 | K18: =J19 | ... N18: =M19
B19: =CAIXA FINAL ACUMULADO | C19: =C18+C17 | D19: =D18+D17 | E19: =E18+E17 | F19: =F18+F17 | G19: =G18+G17 | H19: =H18+H17 | I19: =I18+I17 | J19: =J18+J17 | ... N19: =N18+N17 | O19: =N19
B21: ⚠️ Premissa de fluxo: 60% PIX/à vista | 30% em até 3x | 10% em 6x+. Modelo simplificado — não considera antecipação de recebíveis. Capital de giro inicial: R$ 50.000 (recomendação CFO; ajustar em B41 se mudar). Risco do parcelado: descasamento receita reconhecida vs caixa pode chegar a 60-90 dias.

Sheet 15. Ponto Equilíbrio
A1: PONTO DE EQUILÍBRIO — FATURAMENTO MÍNIMO MENSAL
A3: FÓRMULA E CÁLCULO
B4: Componente | C4: Valor | D4: Origem
B5: Custo fixo total mensal (com pró-labore + INSS) | C5: ='2. Premissas'!C63 | D5: Soma da aba 2 — premissas
B6: Imposto Simples | C6: ='2. Premissas'!C31 | D6: Premissa editável
B7: Taxa cartão média | C7: ='2. Premissas'!C69 | D7: Média ponderada
B8: Inadimplência | C8: ='2. Premissas'!C38 | D8: PCLD 4%
B9: Deduções variáveis totais (impostos + taxa + inad) | C9: ='2. Premissas'!C70 | D9: Soma das 3 deduções
B10: Margem de contribuição efetiva | C10: =1-'2. Premissas'!C70 | D10: =1 - deduções
B12: 🎯 PONTO DE EQUILÍBRIO MENSAL (R$) | C12: ='2. Premissas'!C63/(1-'2. Premissas'!C70) | D12: PE = CF / (1 - deduções variáveis)
B13: Ponto de equilíbrio ANUAL | C13: =C12*12
B14: Margem de segurança recomendada (+30%) | C14: =C12*1.3 | D14: Patamar saudável de operação
A16: COMBINAÇÕES PARA ATINGIR O PE (exemplos)
B17: Combinação | C17: Receita projetada | D17: Atinge PE?
B18: 4 projetos Pro/mês (R$ 4.990 × 4) | C18: =4990*4 | D18: =IF(C18>=$C$12,"✅ Sim","❌ Não")
B19: 3 Start + 1 Pro/mês | C19: =2490*3+4990 | D19: =IF(C19>=$C$12,"✅ Sim","❌ Não")
B20: 2 Pro + 1 Premium | C20: =4990*2+8900 | D20: =IF(C20>=$C$12,"✅ Sim","❌ Não")
B21: 10 contratos Suporte Pro (MRR) | C21: =990*10 | D21: =IF(C21>=$C$12,"✅ Sim","❌ Não")
B22: 8 contratos Suporte Pro + 1 Start | C22: =990*8+2490 | D22: =IF(C22>=$C$12,"✅ Sim","❌ Não")
B23: 2 Start + 1 Pro + 5 Suporte Pro (MIX REALISTA) | C23: =2490*2+4990+990*5 | D23: =IF(C23>=$C$12,"✅ Sim","❌ Não")
B24: 1 Premium + 8 Suporte Pro | C24: =8900+990*8 | D24: =IF(C24>=$C$12,"✅ Sim","❌ Não")
B26: 💡 PE em horas faturáveis: dividir o PE pela hora de venda recomendada (R$ 89-118/h) — equivale a ~140-180h/mês. Isso representa 40-50% da capacidade produtiva total. Operar a partir de R$ 25.000/mês oferece margem de segurança confortável.

Sheet 16. Indicadores
A1: INDICADORES ESTRATÉGICOS (KPIs)
B2: Dashboard de acompanhamento mensal — use as fórmulas como referência
A4: INDICADORES OPERACIONAIS E FINANCEIROS
B5: Indicador | C5: Fórmula | D5: Meta | E5: Como medir / Observação
B6: Ticket médio Projeto 48h | C6: Receita 48h / qtd projetos | D6: R$ 4.500-5.500 | E6: Mix Start/Pro/Premium influencia
B7: MRR (Monthly Recurring Revenue) | C7: Soma das mensalidades ativas no mês | D7: R$ 25.000 até mês 12 | E7: Coração do negócio — KR principal do OKR2
B8: ARR (Annual Recurring Revenue) | C8: MRR × 12 | D8: R$ 300.000 até mês 12 | E8: Para avaliação do negócio
B9: CAC (Custo de Aquisição de Cliente) | C9: Marketing total / clientes novos | D9: < R$ 800 | E9: Payback < 3 meses
B10: LTV (Lifetime Value) | C10: Ticket × meses de retenção × margem | D10: > R$ 5.000 | E10: LTV/CAC ratio > 5
B11: Churn mensal | C11: Cancelamentos / base ativa | D11: < 4% | E11: Crítico para MRR sustentável
B12: Conversão Projeto → Suporte mensal | C12: Clientes em suporte / clientes total | D12: 60% em 12m | 65% em 24m | E12: Mecânicas: bundle, revisão D+30/D+60
B13: Capacidade ocupada | C13: Horas faturáveis / horas alvo | D13: ≤ 80% | E13: Gatilho de contratação > 85% por 2 meses
B14: Receita por sócio | C14: Receita total / 2 sócios | D14: R$ 15-20k mês 12 (realista) | E14: Métrica de saúde individual
B15: Receita por hora produtiva | C15: Receita / horas produtivas | D15: R$ 110-150/h | E15: Indica eficiência de monetização
B16: Margem por linha de serviço | C16: Lucro linha / Receita linha | D16: 48h: 40% | Suporte: 50% | Parceria: ~95% | E16: Identifica linhas a expandir
... B22: Fator R (folha / receita) | C22: Pró-labore × 12 / RBT12 | D22: ≥ 28% (Anexo III) | E22: Crítico fiscal — Resolução CGSN 140/18

Sheet 17. Análise Especialistas
A1: ANÁLISE DOS AGENTES ESPECIALISTAS DO SQUAD
B2: Cada especialista do squad avalia o plano sob sua ótica. Síntese das análises detalhadas.
B4: 🧮 AGENTE CONTÁBIL
B5: Parecer: VIÁVEL com Anexo III ativo. Pró-labore R$ 8k calibrado para Fator R ≥ 28%. Premissa de 12% imposto é CONSERVADORA — efetivo real é 6-8,4% até R$ 30k/mês.
B6: Imposto de 12% é suficiente? | C6: Conservadora demais para a fase inicial. Anexo III com Fator R ≥ 28%: efetivo de 6% até R$ 180k/ano e 8,4% até R$ 360k/ano. A premissa de 12% só se torna realista quando o faturamento ultrapassa R$ 33k/mês. Acima de R$ 28,5k/mês com pró-labore R$ 8k, o Fator R cai abaixo de 28% e a empresa pode despencar para o Anexo V (15,5%) — RISCO CRÍTICO a monitorar mensalmente.
B7: Como pró-labore impacta o PE? | C7: Pró-labore + INSS = R$ 8.880 mensais = 70% dos custos fixos. PE com R$ 8k pró-labore ≈ R$ 16-19k/mês. Se reduzido para R$ 6k (escalonado), PE cai para ~R$ 14k. Recomendação CFO: pró-labore progressivo nos 6 primeiros meses.
B8: Estrutura de custos adequada? | C8: Razoável, com lacunas: faltam previsões de (a) provisão 13º pró-labore + férias proporcionais (CPC 25); (b) certificado digital A1 anual; (c) contingência fiscal 1-2% receita; (d) ISS antecipado em municípios de SP/RJ/BH; (e) provisão cancelamentos 1-3%. Lista completa inserida na aba 4.
B9: DRE está coerente? | C9: Estrutura conforme CPC 26 (R1). Atenção a: (a) receita de exportação Shopify entra com isenção de ISS (art. 18 §14 LC 123/06) — segregar; (b) registrar pró-labore como despesa, não distribuição; (c) manter escrituração completa para distribuição isenta acima do limite presumido (art. 145 Res CGSN 140/18).
B10: Riscos contábeis/fiscais | C10: 1) Desenquadramento Anexo III → V se Fator R cair: +9% de imposto = R$ 2.700/mês a +. 2) Distribuição de lucros acima do limite presumido sem escrituração completa = tributável (Lei 9.249/95). 3) Sócio com participação >10% em outra empresa cuja receita global ultrapasse R$ 4,8 mi/ano = desenquadramento. 4) NFS-e nacional obrigatória desde 2023 — precisa de certificado e credenciamento.
B11: Contador especializado é necessário? | C11: SIM. Honorário R$ 700-1.200/mês para escritório com experiência em TI/agência (vs R$ 195 Contabilizei online). Justifica-se por: gestão mensal do Fator R, segregação de receita de exportação, limite de distribuição isenta, eSocial sócios, NFS-e.
B12: 5 ações OBRIGATÓRIAS antes do 1º faturamento | C12: 1) Registrar LTDA na Junta com CNAEs corretos (6201-5/01 principal + 6202-3/00 + 6209-1/00 + 7319-0/04 + 6311-9/00); 2) Optar pelo Simples até 30 dias após CNPJ; 3) Emitir Certificado A1 + credenciar NFS-e; 4) Estruturar plano de contas + contratar contador especializado; 5) Cadastrar pró-labore no eSocial + formalizar acordo de sócios.
B14: ⚖️ AGENTE JURÍDICO
B15: Parecer: VIÁVEL com cláusulas e estrutura adequadas. SEM Política do Projeto 48h + contrato dual-track + LGPD = NÃO LANÇAR. Risco real de processo no PROCON.
B16: Riscos da promessa '48 horas' | C16: Oferta vinculante (CDC art. 30). Atraso = publicidade enganosa (art. 37 §1º) + direito de cumprimento forçado/rescisão+perdas (art. 35). Cliente B2B (PME) que usa loja como insumo → CC; MEI/PF → CDC. Necessário CONTRATO DUAL-TRACK (B2B + B2C/CDC) + Política Pública obrigatória.
B17: Contrato — cláusulas obrigatórias | C17: 1) Escopo TAXATIVO (art. 114 CC); 2) Cláusula 'Marco Zero' do prazo (pagamento + briefing + assets + aceite Política); 3) Cláusula de suspensão; 4) Aceite + DoD com silêncio = anuência (art. 111 CC, 5 du); 5) Política de revisões (2 incluídas, excedente faturado); 6) Change Request escrito; 7) Mora 1% a.m. + multa 2% + cláusula penal art. 408/411/412 CC (cap 10% do projeto); 8) Cancelamento + taxa mobilização não reembolsável (20-30%); 9) Limitação de responsabilidade = valor pago; 10) Garantia: B2C 90 dias (CDC art. 26 II), B2B 30/90 (CC 445); 11) Confidencialidade mútua; 12) PI: cliente recebe arte final; Impulso retém templates/boilerplate; 13) LGPD: papel + DPA + sub-operadores; 14) Isenção plataformas/integrações de terceiros.
B18: Tipo societário | C18: LTDA (CC arts. 1.052-1.087). Contrato Social com: quotas (não 50/50 puro), administração, pró-labore, distribuição (pode ser desproporcional — art. 1.007), Acordo de Sócios apartado (vesting/cliff/não-competição/buy-sell/arbitragem), CNAEs corretos. CNAE principal 6201-5/01.
B19: LGPD | C19: Papel da Impulso geralmente = OPERADORA (art. 39); pode ser CO-CONTROLADORA em tráfego pago/segmentação. DPA obrigatório. Medidas de segurança (arts. 46-49). Sub-operadores (Shopify/Meta/Google) com cláusula back-to-back. Comunicação de incidentes à ANPD (art. 48). Multa: até 2% do faturamento (cap R$ 50 mi).
B20: Parceria plataformas (Shopify Partners) | C20: Comissão = intermediação (LC 116/03 item 10.02 ou 17.12). Para plataforma estrangeira (Shopify Inc.): EXPORTAÇÃO de serviço → ISS isento (art. 2º I LC 116/03), PIS/COFINS alíquota zero. NÃO confundir com IRRF/CIDE/PIS-COFINS-Importação (esses incidem na remessa AO exterior, não no INGRESSO). Contrato de câmbio obrigatório (Lei 14.286/21).
B21: Mídia paga — RISCO ALTO | C21: NUNCA receber verba de mídia em conta da Impulso → estouro Simples (art. 3º §14 LC 123/06), risco COAF (Lei 9.613/98), exposição cambial. CLIENTE PAGA DIRETO Meta/Google. Impulso cobra apenas FEE de gestão. Cláusula expressa de não-garantia de resultado (art. 39 IV CDC).
B22: Top 5 riscos jurídicos | C22: 1) Publicidade enganosa '48h' sem Política + gatilhos; 2) Receber verba de mídia em conta própria; 3) Ausência de DPA / papel LGPD indefinido; 4) Contrato social 50/50 sem buy/sell (paralisia → dissolução judicial art. 1.034); 5) IP não segregado (perda de ativo intangível).
B23: 7 ações OBRIGATÓRIAS antes da 1ª venda | C23: 1) Registrar LTDA + CNAEs + Simples + IM/IE; 2) Acordo de Sócios (vesting/cliff/buy-sell/arbitragem); 3) Termos de Uso + Política Privacidade do site (LGPD + Marco Civil); 4) Política do Projeto 48 Horas com aceite eletrônico; 5) Contrato dual-track B2B/B2C + Termo Aceite + DPA; 6) Registrar marca IMPULSO no INPI (classes 35/41/42); 7) Seguro RC profissional (E&O) + canal LGPD/DPO.
B25: 💰 AGENTE FINANCEIRO
B26: Parecer: VIÁVEL no Realista (margem 24%, payback 9m). Insustentável no Pessimista. Pró-labore escalonado + foco em MRR são as alavancas-chave.
B27: Viabilidade do modelo | C27: Realista: receita anual R$ 275k, margem 24%, lucro R$ 67k, payback ~9m. Otimista: R$ 427k, margem 44%, payback 4m. Pessimista: receita R$ 115k, prejuízo R$ 67k — INVIÁVEL sem aporte ou ajuste.
B28: Preço mínimo sustentável | C28: Custo/h interno = R$ 34,72 (Custo Fixo Total R$ 12,5k ÷ 360h capacidade). Vender abaixo = prejuízo certo. Preço/h MÍNIMO R$ 58,85 (margem 20%); RECOMENDADO R$ 89,03 (margem 40%); PREMIUM R$ 144,68 (55%). Para alinhar com mercado real (freela R$ 150-400/h, agência R$ 200-600/h), trabalhar com 75% utilização real eleva preço/h recomendado para R$ 118.
B29: Pacote 48h — preço recomendado | C29: Start 32h → R$ 1.781 mínimo / R$ 2.490 sugerido comercial. Pro 70h → R$ 3.561 mínimo / R$ 4.990. Premium 130h → R$ 6.232 mínimo / R$ 8.900. Ancoragem psicológica + colchão p/ desconto.
B30: Mix de receita ideal | C30: 12m: 55% projetos 48h | 20% personalizados | 15% MRR | 5% parceria | 5% tráfego. 24m: 40% / 20% / 25% / 8% / 7%. 36m: 30% / 20% / 30% / 10% / 10%. META: 50% recorrente em 36 meses.
B31: Ponto de equilíbrio | C31: PE = R$ 12.500 / 0,79 = R$ 15.823/mês (com Simples 12% + taxa 5% + inad 4%). Margem de segurança recomendada: operar a partir de R$ 25.000/mês. Em horas: 178h/mês a R$ 89/h (49% da capacidade).
B32: Capital de giro | C32: Burn rate mensal = R$ 12.500. Reserva mínima 3× = R$ 37.500. RECOMENDADA 6× = R$ 75.000. Conservadora 12× = R$ 150.000. Reserva inicial obrigatória ANTES do mês 1: **R$ 50.000** + linha de antecipação de recebíveis pré-aprovada.
B33: Risco do parcelamento | C33: Vender Pro R$ 3.561 em 12x → recebe R$ 296,75/mês (não R$ 3.561 hoje). Se 50% das vendas parcelarem em 6x+, descasamento caixa de 60-90 dias. POLÍTICA: 5% off PIX/à vista; máx 3x sem juros; 6x+ com juros repassados; antecipação só se ROI > custo.
B34: Top 5 riscos financeiros + mitigação | C34: 1) Pró-labore R$ 8k mês 1 inviável → ESCALONAR R$ 3k → R$ 3,5k → R$ 4k condicional a MRR > R$ 10k. 2) Capacidade 360h é teto teórico — usar 270h faturáveis; freela a partir 70% util. 3) Concentração transacional → 5 contratos MRR/mês desde mês 1. 4) Inad B2B 4% + parcelado → política de pagamento agressiva. 5) Key-person (2 sócios) → seguro vida cruzado + SOPs.
B35: Veredito | C35: VIÁVEL no realista com 3 ajustes: (1) pró-labore escalonado; (2) repricing comercial (Start 2.490/Pro 4.990/Premium 8.900); (3) foco agressivo em MRR. Sem ajustes, ainda viável, mas margem cai e payback estende. O upside real do negócio está em virar SaaS-like via MRR.
B37: 🎯 AGENTE DE PLANEJAMENTO ESTRATÉGICO
B38: Parecer: '48h' é GATILHO DE CONVERSÃO, NÃO vantagem sustentável. Sem migrar para 'operador de crescimento' em 24-36m, perde para IA gratuita. Recorrente é o coração.
B39: Posicionamento | C39: Foco/Nicho com diferenciação operacional. Custo puro = suicídio. Diferenciação ampla = cara para 2 sócios. Nicho viável: PMEs físicas migrando para digital + lojistas em SaaS BR (Tray/Nuvemshop) profissionalizando. Proposta: 'Sua loja online profissional no ar em 48 horas — pronta para vender — com método, suporte e crescimento contínuo, sem freelancer sumido nem agência que demora 3 meses.'
B40: '48 horas' é vantagem real? | C40: É GATILHO DE CONVERSÃO, NÃO vantagem sustentável. Qualquer agência ou freelancer copia em 60 dias. Vantagem real = método/processo proprietário por trás das 48h: checklist 80-100 pontos, kit fiscal BR, biblioteca 30+ blocos, integrações pré-configuradas, prompts de IA versionados. '48h' vende; o processo defende.
B41: ICP — 3 personas | C41: 1) CARLA, Lojista Física 42a, boutique R$ 30-150k/mês, vende no DM — ticket R$ 3,5-6k setup + R$ 600-1,2k suporte; canal Insta orgânico + indicação contador/SEBRAE. 2) RODRIGO, Empreendedor DTC 32a, lançando marca, capital R$ 20-80k — ticket R$ 5-12k + R$ 1,5-5k tráfego; canal Google Ads + LinkedIn. 3) MARIANA, Gestora B2B PME 38a, distribuidora migrando catálogo — ticket R$ 8-20k + R$ 1,5-3k; canal LinkedIn outbound + parceria ERPs.
B42: Mercado (TAM/SAM/SOM) | C42: TAM ~R$ 2,4bi (600k lojas SaaS × ticket R$ 4k lifetime serviço). SAM ~R$ 400-450M/ano (30k contratações + 360k×R$ 800×12 suporte). SOM 24m ~R$ 730k/ano (~0,15% SAM). Conclusão: mercado não é restrição — EXECUÇÃO é.
B43: 5 Forças (resumo) | C43: Rivalidade ALTA (agências boutique, freelancers, Shopify Partners BR). Substitutos ALTA E CRESCENTE (Shopify Magic, Wix ADI, Canva sites). Fornecedor MÉDIO-ALTO (dependência plataformas). Cliente ALTO no início, MÉDIO depois. Novos entrantes ALTA (barreira baixíssima). CONCLUSÃO: comoditizável — defesa = nicho + marca + processo + recorrência.
B44: Vantagem competitiva sustentável | C44: Ativos a construir (em ordem): 1) Método Impulso 48h documentado (80-100 checkpoints); 2) Biblioteca templates verticais (moda/beleza/pet/alimentos/B2B); 3) Kit IA proprietário (reduz custo marginal 30-40%); 4) Cases de receita real do cliente (não 'site bonito'); 5) Comunidade Impulso (reduz churn de suporte).
B45: OKRs do 1º ano | C45: O1 — Validar motor comercial: KR1 R$ 480k em 12m; KR2 CAC < R$ 800, payback < 3m; KR3 70+ SQL/mês a partir mês 6. O2 — Construir MRR previsível: KR1 R$ 25k MRR mês 12; KR2 60% conversão setup→suporte; KR3 churn < 4%. O3 — Ativos defensáveis e marca: KR1 método v1.0 documentado mês 4; KR2 12 cases publicados; KR3 10k seguidores combinados sócios.
B46: Riscos estratégicos top 5 | C46: 1) IA generativa (Shopify Magic/Wix ADI) elimina setup básico 24-36m → subir na cadeia, vender vendas. 2) Comoditização → nicho vertical + bundle + recusar baixo ticket. 3) Dependência plataformas → multi-plataforma + comissão <15% receita. 4) Burnout sócios → cap 5 projetos/sócio/mês + playbook + férias. 5) Falta de diferenciação → investir nos 5 ativos.
B47: Trade-offs explícitos — NÃO fazer | C47: NÃO atende enterprise/VTEX/Magento; NÃO faz projeto <R$ 3.500; NÃO entrega site sem suporte mensal anexado; NÃO faz 'só design' ou 'só consultoria avulsa'; NÃO trabalha com cliente sem CNPJ/produto/capital; NÃO faz marketplace-only; NÃO promete prazo fora do método; NÃO aceita horas avulsas no suporte; NÃO compete em licitação pública/RFP.
B48: Veredito | C48: Defensável hoje? Parcialmente. Sustentável aos 24m? SIM, condicional a: (1) reposicionar de 'implementador' para 'operador de crescimento de PMEs digitais'; (2) recorrente vira CORAÇÃO (50% em 24m); (3) verticalizar em 2-3 nichos. Sem ajustes: R$ 600k/ano com 2 sócios exaustos competindo com IA gratuita em 2027. Com ajustes: R$ 1,5-2M aos 36m, margem 35-45%, EV vendável.
B50: ⚙️ AGENTE DE OPERAÇÕES DIGITAIS E E-COMMERCE
B51: Parecer: 'Todos os produtos, todas as integrações em 48h' é ARMADILHA. Com escopo brutalmente recortado (até 20 SKUs), o modelo cabe — e gera throughput sustentável.
B52: Viabilidade real do 48h | C52: Shopify 20 SKUs: 26-66h de execução com 2 pessoas em paralelo — CABE em 48h SE pré-condições 100% fechadas. WooCommerce: 40-90h equivalente — NÃO CABE em 48h salvo escopo mínimo. Site institucional 5-8 páginas: 21-42h — cabe. 50-100 SKUs, integração ERP/OMS, marketplace, gateway custom — NÃO CABEM.
B53: 3 pacotes recomendados | C53: START: até 15 SKUs, 5 páginas, 1 gateway, 1 frete, 3 reuniões, 1 treinamento, 7d suporte. Horas: 22/32/45. PRO: até 50 SKUs, 8 páginas, 2 gateways, 2 fretes, 1 integração (Bling OU Tiny OU RD), 15d suporte. Horas: 45/70/100. PREMIUM: até 150 SKUs, 12 páginas, 2 integrações (ERP+marketplace), automações carrinho, 2 landing pages, 30d suporte. Horas: 90/130/180. WooCommerce só PRO/PREMIUM com +30% prazo/preço — DESENCORAJAR.
B54: Capacidade operacional realista | C54: Bruto: 352h (2 sócios × 22du × 8h). Descontos: comercial 15% + atendimento 10% + pós-venda 10% + admin 8% + gestão 7% = 50% só. EXECUÇÃO PURA = ~176h/mês combinada. Alvo ≤80% = 144h para projetos. Mix sustentável: 2 Start + 1 Pro (134h) OU 1 Start + 1 Premium (162h). Premium a cada 2 meses máx enquanto dupla.
B55: Suporte recorrente — limites | C55: Essencial 4h: 4-5 contratos/sócio = 8-10 total. Pro 10h: 2-3/sócio = 4-6 total. Growth 20h: 1-2/sócio = 2-4 total. Cada sócio MÁX 50% capacidade (90h) em suporte.
B56: Top 10 riscos operacionais + mitigação | C56: 1) Cliente atrasa assets → cláusula pausa cronômetro + 50% upfront. 2) Gateway em KYC → pré-condição rígida. 3) Doença sócio → buffer 20% + SOPs + freela plug-in. 4) Escopo creep → tabela adicionais + change request formal. 5) Cliente revende '48h' como milagre → FAQ visível 'o que NÃO entra'. 6) Pós-venda canibaliza execução → suporte pago obrigatório dia 30. 7) Plataforma quebra integração → especializar Shopify+Nuvemshop. 8) NPS baixo treinamento → videoteca + sessão gravada. 9) IA caída → templates locais + SOP fallback. 10) Inadimplência pós go-live → 50/40/10 + DNS sob Impulso até pagamento.
B57: IA: onde dá ganho REAL ≥30% | C57: Descrições de produto 30-40%; copy institucional + políticas 40-60%; SEO title/meta/alt em massa 40%; tradução 50%; FAQ a partir de transcrição 50%. ONDE NÃO DÁ (<10%): briefing, decisão UX, QA crítico (checkout/fiscal/pixel), gateway/frete/domínio, treinamento ao vivo, negociação comercial.
B58: SOPs/checklists INDISPENSÁVEIS antes da 1ª venda | C58: 1) Checklist pré-condições D-5 (cliente assina); 2) SOP onboarding (kickoff/kit boas-vindas/acessos); 3) SOP implementação Shopify (60+ itens); 4) SOP implementação WordPress/Woo; 5) Checklist QA pré go-live (checkout/mobile/emails/fiscal/LGPD/pixels); 6) SOP handover + treinamento (roteiro + videoteca + termo aceite); 7) SOP pós-venda 30 dias.
B59: Definition of Done | C59: Loja Shopify: compra teste real (cartão+Pix+boleto); e-mails transacionais renderizados; responsivo iOS/Android+Chrome/Safari/Edge; GA4+Pixel+GTM disparando view_item/add_to_cart/begin_checkout/purchase validados; SEO title/meta únicos + sitemap; LGPD: política+cookie banner+e-mail DPO; HTTPS+redirect www↔raiz; backup salvo; termo aceite assinado; owner 100% no cliente.
B60: Gatilhos para 3º profissional | C60: Sustentado por 2 meses: backlog > 200h, capacidade > 85%, recusa ≥2 projetos qualificados/mês, suporte > 50h combinado, NPS < 8 ou atraso > 20%, MRR ≥ R$ 20k (sustenta CLT-flex R$ 6-9k all-in). Perfil: IMPLEMENTADOR PLENO Shopify/Tray (não sênior). Sócios sobem para vendas + suporte estratégico + conteúdo.
B61: Veredito | C61: SIM, lançar com modificações INEGOCIÁVEIS: (1) renomear 'Express 48h úteis' padrão + 'Sprint 48h corridas' premium +40%; (2) escopo TAXATIVO máx 20 SKUs/1 gateway/1 frete/4 páginas/Shopify+Nuvemshop+Tray (Woo fora); (3) pré-condições D-5 com pausa cronômetro; (4) 50/40/10 + DNS sob Impulso; (5) DoD no contrato; (6) target 2 Start + 1 Pro/mês ou 1 Premium; (7) SOPs 1-7 + videoteca antes da 1ª venda; (8) marketing com 'o que NÃO entra' visível; (9) suporte recorrente obrigatório dia 30; (10) revisão trimestral horas reais vs estimadas. Sem isso: NÃO LANÇAR.

Sheet 18. Análise Crítica
A1: ANÁLISE CRÍTICA GERAL — DEVIL'S ADVOCATE
B2: Pressure-test honesto das premissas. Atacar a ideia, respeitar a pessoa.
B4: O modelo do Projeto 48 Horas é viável? | C4: SIM, com escopo recortado. O '48h corridas com todos os produtos e integrações' é falso por design. O '48h úteis com até 20 SKUs, 1 gateway, 1 frete, plataformas Shopify/Nuvemshop/Tray' é defensável, lucrativo e operacionalmente sustentável.
B5: Qual escopo máximo deve ser prometido? | C5: Loja Shopify/Nuvemshop/Tray: 20 SKUs, 5 páginas, 1 gateway, 1 frete, GA4+Pixel padrão, SEO on-page básico, 1 sessão treinamento (60min), 7 dias suporte. Site institucional: até 8 páginas.
B6: Qual escopo NÃO deve ser prometido? | C6: Migração de plataforma; +30 SKUs; tema customizado (código); integração ERP/OMS/PDV; multi-idioma; marketplace (ML/Amazon); assinaturas; B2B com tabela de preço; app mobile; blog populado; fotografia; copywriting longo; tradução. WooCommerce no regime de 48h.
B7: O preço sugerido cobre o esforço real? | C7: Sim, no nível recomendado (Start R$ 2.490 / Pro R$ 4.990 / Premium R$ 8.900). Margem 40% considerando 12% imposto + 5% taxa + 4% inad. Vender abaixo do preço mínimo (R$ 1.781 / R$ 3.561 / R$ 6.232) = prejuízo certo.
B8: O modelo depende demais dos 2 sócios? | C8: SIM. Risco de key-person crítico. Doença/saída de 1 sócio = -50% capacidade. Mitigação: SOPs documentados, seguro de vida cruzado, freela plug-in pré-aprovado, reserva 6 meses.
B9: Quando contratar a 3ª pessoa? | C9: Gatilhos quantitativos (sustentados por 2 meses): backlog vendido > 200h; capacidade > 85%; recusa ≥2 projetos/mês; suporte > 50h combinado; NPS < 8 ou atraso > 20%; MRR ≥ R$ 20k. Perfil: implementador PLENO (não sênior) Shopify/Tray, CLT-flex ou PJ R$ 5-7k.
B10: Qual serviço tende a ser mais lucrativo? | C10: 1) Parceria com plataformas: ~95% margem líquida (receita passiva, custo zero). 2) Suporte mensal Growth: ~50% margem. 3) Projetos personalizados Premium: 45%. 4) Projeto 48h Premium: 40%. 5) Projeto 48h Start: 35%.
B11: Qual serviço tende a gerar mais recorrência? | C11: Suporte mensal (MRR) — coração da tese. Parceria com plataformas — recorrência passiva. Tráfego pago — sticky por dependência operacional. Projeto 48h gera recorrência SOMENTE se converte para suporte mensal (meta: 60% conversão em 12m).
B12: Quais serviços devem ser evitados? | C12: 1) Projetos abaixo de R$ 2.000 (canibalizam capacidade). 2) WooCommerce no formato 48h. 3) VTEX/Magento (enterprise). 4) Marketplace-only. 5) Consultoria avulsa sem entregável. 6) Migração com escopo aberto. 7) Receber verba de mídia em conta (risco fiscal).
B13: Quais serviços devem ser cobrados como EXTRA? | C13: Tudo que não estiver no escopo taxativo: SKUs adicionais (R$/SKU), páginas adicionais, integrações além das listadas, copywriting customizado (R$/página), fotografia, banco de imagens premium, design de logo, sessões extra de treinamento, suporte pós-go-live além do contratado, change requests.
B14: Quais premissas precisam ser validadas no mercado? | C14: 1) Disposição real dos clientes a pagar R$ 4.990 em Pro (PoC: 5 clientes em 60 dias). 2) Taxa de conversão setup→suporte de 60% (PoC: contratos em 6 meses). 3) CAC < R$ 800 (depende de canal escolhido). 4) Ganho real de produtividade com IA = 25% (medir nos primeiros 3 projetos). 5) Capacidade 360h é teto — validar com 1º trimestre real.
B15: Pró-labore de R$ 8.000 é sustentável no início? | C15: NÃO no mês 1 do realista (PE só atinge no mês 4). RECOMENDAÇÃO: escalonar — R$ 3.000/sócio (mês 1-3) → R$ 3.500 (4-6) → R$ 4.000 (7+) condicional a MRR > R$ 10k. Diferencial vai para reserva de capital de giro. ATENÇÃO FISCAL: pró-labore total < R$ 6.700/mês pode quebrar Fator R ≥ 28% e jogar a empresa no Anexo V (15,5% imposto vs 6%). Pró-labore mínimo p/ sustentar Anexo III em R$ 25k/mês de receita = ~R$ 7.000/mês.
B16: Faturamento mínimo mensal para operar? | C16: PE = R$ 15.823/mês (com 12% imposto + 5% taxa + 4% inad). Operar com folga: R$ 25.000/mês. Para gerar lucro saudável (margem > 20%): R$ 30.000/mês.
B18: 🔥 VEREDITO DEVIL'S ADVOCATE
B19: 🟡 PROSSEGUIR COM REVISÕES CRÍTICAS. A tese resiste ao ataque NOS PARÂMETROS REALISTAS. Não resiste com a promessa original de '48h para tudo'. Os 3 pontos de fragilidade real são: 1) PRÓ-LABORE: começar com R$ 8k mês 1 destrói o caixa. Escalonar é mandatório. 2) ESCOPO DA OFERTA: '48h corridas para tudo' é commodities-promise inexequível. Recortar para escopo taxativo (Start/Pro/Premium com limites duros) protege a operação E aumenta percepção de profissionalismo. 3) DEPENDÊNCIA DE IA GENERATIVA: a tese estratégica precisa evoluir nos 24-36 meses para 'operador de crescimento de PMEs', não 'implementador de loja'. Quem só monta loja perde para Shopify Magic/Wix ADI até 2027. Critério de falsificação: se aos 6 meses NÃO houver pelo menos R$ 10k MRR consolidado e taxa de conversão setup→suporte abaixo de 30%, a tese falha — pivotar para verticalização ou outro modelo.

Sheet 19. Recomendações
A1: RECOMENDAÇÕES FINAIS DO SQUAD
B2: Ações objetivas e prontas para execução.
B4: Melhor modelo de precificação | C4: Pacote fechado com escopo TAXATIVO + preço de tabela público + change request formal para adicionais. Hora avulsa SOMENTE para suporte excedente e consultoria pontual. Mensalidades com vigência mínima de 12m (B2B).
B5: Pacote 48h para entrada no mercado | C5: Pacote PRO (R$ 4.990) como gancho principal. Start (R$ 2.490) só com promo de lançamento para construir cases. Premium (R$ 8.900) para clientes qualificados.
B6: Preço mínimo do Projeto 48 Horas | C6: Start: R$ 1.781 | Pro: R$ 3.561 | Premium: R$ 6.232 — NUNCA vender abaixo disso (margem mínima 20%).
B7: Preço recomendado | C7: Start: R$ 2.490 | Pro: R$ 4.990 | Premium: R$ 8.900 — preço comercial sugerido com colchão para descontos.
B8: Preço premium (sem desconto) | C8: Start: R$ 2.893 | Pro: R$ 5.787 | Premium: R$ 10.127 — preço de ancoragem para clientes que aceitam pagar mais por sprint dedicado.
B9: Como proteger de escopo aberto | C9: 1) Escopo TAXATIVO no contrato (lista exaustiva de incluso). 2) Política do Projeto 48h pública. 3) Cláusula de Change Request escrito + valor por hora. 4) Pacote de adicionais publicado. 5) Briefing assinado eletronicamente. 6) Pré-condições D-5. 7) Aceite + DoD com silêncio = anuência (5 du).
B10: Como transformar projeto em receita recorrente | C10: 1) Bundle de saída: setup já inclui 30 dias suporte cortesia + oferta 20% off se contratar em 7 dias. 2) Revisão D+30 e D+60 com sócio (mostra dados → abre upsell). 3) Suporte em camadas com 'próximo degrau' claro. 4) Comunidade Impulso acessível só a clientes recorrentes. 5) SLA visível no contrato.
B11: Como vender suporte mensal | C11: Foco comercial: 70% do esforço de vendas no suporte mensal, não em projetos. Meta agressiva: 5 contratos novos MRR/mês desde mês 1. Oferta no fechamento do projeto (timing crítico). Mecânica de auto-renovação.
B12: Como estruturar contrato | C12: Contrato dual-track (B2B/CC + B2C/CDC). Cláusulas obrigatórias (ver aba 17 — Jurídico). Termo de Aceite/Briefing com Marco Zero. DPA LGPD. Política do Projeto 48 Horas pública. Forma de pagamento 50/40/10. Foro Sede da Impulso (B2B) ou domicílio cliente (B2C).
B13: Como evitar prejuízo com cartão parcelado | C13: 1) 5% off PIX/à vista. 2) Máximo 3x sem juros. 3) 6x+ com juros repassados ao cliente. 4) Antecipação de recebíveis APENAS se ROI > custo (2-3% a.m.). 5) Reserva de capital de giro R$ 50k antes do mês 1.
B14: Como usar IA sem comprometer qualidade | C14: IA SIM para: descrições de produto (30-40% ganho), copy institucional + políticas (40-60%), SEO em massa (40%), tradução (50%), FAQ a partir de transcrição (50%). IA NÃO para: briefing, decisão UX, QA crítico (checkout/fiscal/pixel), gateway/frete/domínio, treinamento ao vivo, negociação. Templates locais como fallback se a IA cair.
B15: Como validar a aceitação do mercado | C15: Soft launch nos primeiros 90 dias com 5-10 clientes-piloto. Coletar: taxa de fechamento da proposta; tempo real vs prometido; NPS pós-projeto; conversão para suporte; CAC por canal. Pivotar pacotes/preço se desvio > 20% nas premissas.
... B18: Capital de giro | C18: R$ 50.000 ANTES do mês 1 (recomendação CFO conservadora). Aumentar para R$ 75.000 (6× burn) se cenário pessimista for risco real. Linha de antecipação pré-aprovada como segurança.

Sheet 20. Plano 90 Dias
A1: PLANO DE AÇÃO — PRIMEIROS 90 DIAS DA IMPULSO
B2: Checklist executável. Marque [✓] quando concluir. Responsável e prazo por iniciativa.
B4: # | C4: Ação | D4: Prazo | E4: Responsável | F4: Status
A5: 🟦 DIAS 1-30 — ESTRUTURAÇÃO LEGAL, COMERCIAL E OPERACIONAL
B6: 1 | C6: Registrar LTDA na Junta Comercial + CNAEs corretos | D6: D+7 | E6: Sócio 1 + Contador | F6: ☐ Pendente
B7: 2 | C7: Optar pelo Simples Nacional + emitir Certificado A1 | D7: D+10 | E7: Contador | F7: ☐ Pendente
B8: 3 | C8: Credenciar NFS-e nacional + município | D8: D+15 | E8: Contador | F8: ☐ Pendente
B9: 4 | C9: Assinar Acordo de Sócios (vesting/cliff/buy-sell) | D9: D+10 | E9: Advogado + sócios | F9: ☐ Pendente
B10: 5 | C10: Aprovar contrato dual-track B2B/B2C + Termo Aceite + DPA | D10: D+15 | E10: Advogado | F10: ☐ Pendente
B11: 6 | C11: Publicar Política do Projeto 48 Horas com aceite eletrônico | D11: D+15 | E11: Advogado + sócios | F11: ☐ Pendente
B12: 7 | C12: Publicar Termos de Uso + Política de Privacidade | D12: D+20 | E12: Advogado | F12: ☐ Pendente
B13: 8 | C13: Registrar marca IMPULSO no INPI (classes 35/41/42) | D13: D+30 | E13: Advogado | F13: ☐ Pendente
B14: 9 | C14: Definir pacotes 48h (Start/Pro/Premium) com escopo TAXATIVO | D14: D+15 | E14: Sócios | F14: ☐ Pendente
B15: 10 | C15: Definir planos de suporte (Essencial/Pro/Growth) | D15: D+15 | E15: Sócios | F15: ☐ Pendente
B16: 11 | C16: Criar tabela de preços + descontos públicos | D16: D+18 | E16: Sócios | F16: ☐ Pendente
B17: 12 | C17: Documentar SOPs 1-7 (pré-condições, onboarding, Shopify, Woo, QA, handover, pós-venda) | D17: D+25 | E17: Sócios | F17: ☐ Pendente
... B25: 20 | C25: Contratar seguro RC profissional (E&O) | D25: D+30 | E25: Sócios | F25: ☐ Pendente
A26: 🟨 DIAS 31-60 — PROSPECÇÃO E PRIMEIROS CLIENTES
B27: 1 | C27: Lançar conta Instagram + YouTube Shorts (rosto dos sócios) | D27: D+35 | E27: Sócio 1 | F27: ☐
B28: 2 | C28: Publicar lead magnet: 'Checklist 48h - 47 coisas que sua loja precisa' | D28: D+33 | E28: Sócios | F28: ☐
B29: 3 | C29: Abrir formulário 'Diagnóstico Express 30min' (gratuito) | D29: D+33 | E29: Sócios | F29: ☐
B30: 4 | C30: Iniciar outbound LinkedIn (50 mensagens/sem por sócio) | D30: D+35 | E30: Sócios | F30: ☐
B31: 5 | C31: Cadastrar como Shopify Partner / Tray Partner / Nuvemshop Expert | D31: D+35 | E31: Sócio 2 | F31: ☐
B32: 6 | C32: Definir 1ª campanha Meta Ads (R$ 3-5k/mês, segmentação ICP) | D32: D+40 | E32: Sócios | F32: ☐
B33: 7 | C33: Prospectar contadores parceiros para indicação cruzada (10 contatos) | D33: D+45 | E33: Sócios | F33: ☐
B34: 8 | C34: Fechar 1º cliente Projeto 48h (validação de processo) | D34: D+50 | E34: Sócios | F34: ☐
B35: 9 | C35: Fechar 2º cliente (ajustar tempo real vs prometido) | D35: D+55 | E35: Sócios | F35: ☐
B36: 10 | C36: Fechar 3º cliente (consolidar SOPs) | D36: D+60 | E36: Sócios | F36: ☐
B37: 11 | C37: Coletar NPS pós-projeto + ajustar processo se < 8 | D37: D+60 | E37: Sócios | F37: ☐
B38: 12 | C38: Oferecer suporte mensal aos primeiros clientes (meta: 2 conversões) | D38: D+60 | E38: Sócios | F38: ☐
... B40: 14 | C40: Revisão semanal de horas reais vs estimadas (ajustar preço se desvio > 15%) | D40: Semanal | E40: Sócios | F40: ☐
A41: 🟩 DIAS 61-90 — OTIMIZAÇÃO, RECORRÊNCIA E PRÉ-ESCALA
B42: 1 | C42: Revisar pacotes 48h com base nos primeiros 3-5 projetos | D42: D+65 | E42: Sócios | F42: ☐
B43: 2 | C43: Ajustar preços se margem real divergir > 15% da projetada | D43: D+65 | E43: Sócios | F43: ☐
B44: 3 | C44: Formalizar parceria com Shopify/Tray/Nuvemshop (receber comissões) | D44: D+70 | E44: Sócios | F44: ☐
B45: 4 | C45: Criar processo comercial documentado (funil + scripts + propostas) | D45: D+75 | E45: Sócios | F45: ☐
B46: 5 | C46: Meta: 6 clientes Projeto 48h fechados nos primeiros 90 dias | D46: D+90 | E46: Sócios | F46: ☐
B47: 6 | C47: Meta: 3 contratos de suporte mensal ativos (MRR > R$ 3.000) | D47: D+90 | E47: Sócios | F47: ☐
B48: 7 | C48: Atingir 60% de conversão setup → suporte mensal | D48: D+90 | E48: Sócios | F48: ☐
B49: 8 | C49: Publicar 3 cases com receita real do cliente | D49: D+90 | E49: Sócios | F49: ☐
B50: 9 | C50: Analisar capacidade real e gargalos (planejar 3º profissional) | D50: D+85 | E50: Sócios | F50: ☐
B51: 10 | C51: Revisar metas O1/O2/O3 dos OKRs e definir KRs do trimestre seguinte | D51: D+90 | E51: Sócios | F51: ☐
B52: 11 | C52: Criar v1.0 do Método Impulso 48h documentado (playbook + blocos + IA) | D52: D+90 | E52: Sócios | F52: ☐
B53: 12 | C53: Revisão financeira: faturamento atingido vs PE, ajustar pró-labore | D53: D+90 | E53: Sócios + Contador | F53: ☐
A55: 🎯 METAS DOS 90 DIAS (resumo)
B56: ✅ 6 clientes Projeto 48h fechados
B57: ✅ 3 contratos de suporte mensal ativos (MRR > R$ 3.000)
B58: ✅ Taxa de conversão setup → suporte ≥ 60%
B59: ✅ NPS médio > 8
B60: ✅ Faturamento total 90d > R$ 25.000
B61: ✅ Método Impulso 48h v1.0 documentado
B62: ✅ 3 cases publicados com receita real do cliente
B63: ✅ Estrutura jurídica, contábil e operacional 100% pronta
